Workbook
Name Slicer_Region: #N/A
Name Slicer_Country: #N/A
Name Slicer_Channel: #N/A
Name Slicer_Salesperson: #N/A
Name Slicer_ProductCategory: #N/A
Name Slicer_OrderDate: #N/A

Sheet Data
A1: OrderID | B1: OrderDate | C1: RequiredDate | D1: Region | E1: Country | F1: City | G1: CustomerSegment | H1: Channel | I1: Salesperson | J1: ProductCategory | K1: SKU | L1: UnitCost | M1: UnitPrice | N1: DiscountPct | O1: Quantity
A2: ORD-2024-275203 | B2: 45362 | C2: 45388 | D2: Africa | E2: Kenya | F2: Kisumu | G2: Corporate | H2: Retail | I2: C. Otieno | J2: Components | K2: CMP-8270 | L2: 279.24 | M2: 608.9 | N2: 0.112 | O2: 9
A3: ORD-2024-358795 | B3: 45588 | C3: 45587 | D3: Africa | E3: Nigeria | F3: Port Harcourt | G3: Education | H3: Online | I3: J. Njeri | J3: Printers | K3: PRN-9322 | L3: 1084.39 | M3: 759.33 | N3: 0.237 | O3: 31
A4: ORD-2023-373538 | B4: 44985 | C4: 45010 | D4: Africa | E4: Kenya | F4: Nairobi | G4: Corporate | H4: Retail | I4: I. Johnson | J4: Networking | K4: NET-9666 | L4: 1460.76 | M4: -30.66 | N4: 0.131 | O4: 12
A5: ORD-2025-168148 | B5: 45745 | C5: 45749 | D5: Africa | E5: Nigeria | F5: Lagos | G5: Non-Profit | H5: Marketplace | I5: G. Dubois | J5: Phones | K5: PHN-4556 | L5: 259.93 | M5: 255.94 | N5: 0.072 | O5: 22
A6: ORD-2023-824839 | B6: 45266 | C6: 45291 | D6: Asia | E6: Japan | F6: Osaka | G6: Consumer | H6: Retail | I6: L. Okafor | J6: Printers | K6: PRN-8041 | L6: 663.03 | M6: 813.51 | N6: 0.102 | O6: 15
A7: ORD-2023-723587 | B7: 44928 | C7: 44931 | D7: Americas | E7: Canada | F7: Toronto | G7: Corporate | H7: Distributor | I7: B. Chen | J7: Laptops | K7: LAP-8555 | L7: 315.87 | M7: 591.68 | N7: 0 | O7: 7
A8: ORD-2024-336584 | B8: 45653 | C8: 45671 | D8: Asia | E8: India | F8: Bengaluru | G8: Small Business | H8: Marketplace | I8: E. Garcia | J8: Monitors | K8: MON-8629 | L8: 586.07 | M8: 845.97 | N8: 0.147 | O8: 4
A9: ORD-2023-112666 | B9: 44941 | C9: 44939 | D9: Africa | E9: Nigeria | F9: Abuja | G9: Education | H9: Online | I9: O. Wang | J9: Printers | K9: PRN-6276 | L9: 28.38 | M9: 47.22 | N9: 0.194 | O9: 18
A10: ORD-2024-589570 | B10: 45416 | C10: 45441 | D10: Africa | E10: Nigeria | F10: Abuja | G10: Non-Profit | H10: Marketplace | I10: O. Wang | J10: Monitors | K10: MON-6892 | L10: 1295.34 | M10: 2530.81 | N10: 0.031 | O10: 6
A11: ORD-2025-997421 | B11: 45798 | C11: 45817 | D11: Americas | E11: Brazil | F11: São Paulo | G11: Non-Profit | H11: Online | I11: A. Patel | J11: Components | K11: CMP-3731 | L11: 1331.38 | M11: 2309.56 | N11: 0.149 | O11: 31
A12: ORD-2024-210687 | B12: 45319 | C12: 45331 | D12: Europe | E12: Germany | F12: Berlin | G12: Corporate | H12: Online | I12: G. Dubois | J12: Accessories | K12: ACC-7938 | L12: 644.17 | M12: 700.12 | N12: 0.006 | O12: 23
A13: ORD-2025-515515 | B13: 45660 | C13: 45680 | D13: Asia | E13: Japan | F13: Osaka | G13: Corporate | H13: Distributor | I13: F. Müller | J13: Phones | K13: PHN-7019 | L13: 908.6 | M13: 691.37 | N13: 0.25 | O13: 20
... A34: ORD-2025-474710 | B34: 45862 | C34: 45875 | D34: Africa | E34: South Africa | F34: Johannesburg | G34: Education | H34: Marketplace | I34: D. Smith | J34: Networking | K34: NET-7966 | L34: 1463.9 | M34: 2633.02 | N34: 0.084 | O34: 4
A35: ORD-2024-629525 | B35: 45400 | C35: 45420 | D35: Europe | E35: United Kingdom | F35: London | G35: Non-Profit | I35: D. Smith | J35: Laptops | K35: LAP-9932 | L35: 645.33 | M35: 1321.85 | N35: 0 | O35: 10
A36: ORD-2024-167215 | B36: 45527 | C36: 45525 | D36: Africa | E36: South Africa | F36: Johannesburg | G36: Education | H36: Retail | I36: E. Garcia | J36: Components | K36: CMP-1559 | L36: 1432.52 | M36: 3036.87 | N36: 0 | O36: 9
A37: ORD-2023-864121 | B37: 45012 | C37: 45038 | D37: Asia | E37: India | F37: Delhi | G37: Non-Profit | H37: Marketplace | I37: J. Njeri | J37: Printers | K37: PRN-4506 | L37: 178.53 | M37: 199.37 | N37: 0.101 | O37: 37
A38: ORD-2024-692673 | B38: 45358 | C38: 45376 | D38: Europe | E38: Germany | F38: Munich | G38: Corporate | H38: Online | I38: B. Chen | J38: Components | K38: CMP-7617 | L38: 712.84 | M38: 927.51 | N38: 0.243 | O38: 27
A39: ORD-2025-718992 | B39: 45832 | C39: 45848 | D39: Asia | E39: China | F39: Shanghai | G39: Enterprise | H39: Direct | I39: N. Brown | J39: Components | K39: CMP-8390 | L39: 757.19 | M39: 1735.41 | N39: 0.136 | O39: 8
A40: ORD-2024-599522 | B40: 45401 | C40: 45418 | D40: Africa | E40: Nigeria | F40: Port Harcourt | G40: Non-Profit | H40: Online | I40: A. Patel | J40: Printers | K40: PRN-7303 | L40: 865.33 | M40: 1395.64 | N40: 0.175 | O40: 13
A41: ORD-2023-651638 | B41: 45094 | C41: 45101 | D41: Americas | E41: USA | F41: San Francisco | G41: Corporate | H41: Retail | I41: I. Johnson | J41: Printers | K41: PRN-6536 | L41: 313.99 | M41: 454.42 | N41: 0.129 | O41: 9
A42: ORD-2024-635626 | B42: 45531 | C42: 45554 | D42: Europe | E42: Germany | F42: Berlin | G42: Small Business | H42: Direct | I42: D. Smith | J42: Monitors | K42: MON-9967 | L42: 1024.01 | M42: 1580.97 | N42: 0.037 | O42: 27
A43: ORD-2024-296582 | B43: 45302 | C43: 45324 | D43: Africa | E43: South Africa | F43: Durban | G43: Consumer | H43: Online | I43: K. Singh | J43: Networking | K43: NET-1412 | L43: 1206.2 | M43: 1759.79 | N43: 0 | O43: 6
A44: ORD-2024-998320 | B44: 45590 | C44: 45610 | D44: Africa | E44: Kenya | F44: Mombasa | G44: Corporate | H44: Direct | I44: H. Kim | J44: Printers | K44: PRN-3143 | L44: 1396.48 | M44: 3204.5 | N44: 0.318 | O44: 14
A45: ORD-2025-820255 | B45: 45806 | C45: 45828 | D45: Europe | E45: Germany | F45: Berlin | G45: Corporate | H45: Direct | I45: A. Patel | J45: Printers | K45: PRN-9787 | L45: 483.47 | M45: 1135.43 | N45: 0.146 | O45: 11
A46: ORD-2024-389336 | B46: 45432 | C46: 45445 | D46: Americas | E46: Canada | F46: Vancouver | G46: Enterprise | H46: Marketplace | I46: K. Singh | J46: Components | K46: CMP-5946 | L46: 675.43 | M46: 996.36 | N46: 0.182 | O46: 22
A47: ORD-2023-308124 | B47: 45035 | C47: 45046 | D47: Asia | E47: India | F47: Delhi | G47: Small Business | H47: Retail | I47: A. Patel | J47: Networking | K47: NET-2062 | L47: 826.55 | M47: 1397.05 | N47: 0.169 | O47: 28
... A77: ORD-2023-722117 | B77: 45187 | C77: 45207 | D77: Asia | E77: India | F77: Delhi | G77: Small Business | H77: Direct | I77: B. Chen | J77: Components | K77: CMP-1009 | L77: 825.64 | M77: 1108.43 | N77: 0.114 | O77: 7
A78: ORD-2024-446699 | B78: 45532 | C78: 45560 | D78: Americas | E78: Brazil | F78: Rio de Janeiro | G78: Non-Profit | H78: Online | J78: Accessories | K78: ACC-4490 | L78: 1394.65 | M78: 3144.1 | N78: 0.134 | O78: 13
A79: ORD-2024-451005 | B79: 45473 | C79: 45471 | D79: Americas | E79: Brazil | F79: Rio de Janeiro | G79: Small Business | H79: Direct | I79: L. Okafor | J79: Accessories | K79: ACC-9162 | L79: 1112.98 | M79: 2095.73 | N79: 0.072 | O79: 17
A80: ORD-2023-290279 | B80: 45091 | C80: 45093 | D80: Europe | E80: United Kingdom | F80: Manchester | G80: Non-Profit | H80: Direct | I80: K. Singh | J80: Components | K80: CMP-5820 | L80: 357.36 | M80: 703.62 | N80: 0.257 | O80: 20
A81: ORD-2024-192263 | B81: 45617 | C81: 45647 | D81: Europe | E81: France | F81: Marseille | G81: Small Business | H81: Direct | I81: I. Johnson | J81: Monitors | K81: MON-7943 | L81: 1122.68 | M81: 1997.19 | N81: 0.186 | O81: 3
A82: ORD-2023-159379 | B82: 44965 | C82: 44968 | D82: Africa | E82: South Africa | F82: Cape Town | G82: Corporate | H82: Direct | I82: M. Rossi | J82: Networking | K82: NET-5018 | L82: 1410.05 | M82: 2763.95 | N82: 0.161 | O82: 26
A83: ORD-2023-343322 | B83: 45157 | C83: 45181 | D83: Americas | E83: Canada | F83: Vancouver | G83: Enterprise | H83: Retail | I83: I. Johnson | J83: Printers | K83: PRN-9669 | L83: 1183.95 | M83: 1503.53 | N83: 0.241 | O83: 16
A84: ORD-2025-114382 | B84: 45791 | C84: 45801 | D84: Europe | E84: France | F84: Paris | G84: Small Business | H84: Marketplace | I84: K. Singh | J84: Components | K84: CMP-2865 | L84: 170.39 | M84: 388.04 | N84: 0.084 | O84: 15
A85: ORD-2025-488349 | B85: 45770 | C85: 45769 | D85: Americas | E85: USA | F85: San Francisco | G85: Non-Profit | H85: Distributor | I85: D. Smith | J85: Monitors | K85: MON-3371 | L85: 23.24 | M85: 44.57 | N85: 0.215 | O85: 15
A86: ORD-2025-330203 | B86: 45741 | C86: 45764 | D86: Europe | E86: United Kingdom | F86: London | G86: Consumer | H86: Retail | I86: H. Kim | J86: Networking | K86: NET-7166 | L86: 1421.19 | M86: 1808.26 | N86: 0.104 | O86: 13
A87: ORD-2023-841426 | B87: 45282 | C87: 45283 | D87: Africa | E87: South Africa | F87: Cape Town | G87: Non-Profit | H87: Marketplace | I87: D. Smith | J87: Components | K87: CMP-4531 | L87: 1186.18 | M87: 1285.09 | N87: 0.07 | O87: 11
A88: ORD-2024-594592 | B88: 45388 | C88: 45407 | D88: Asia | E88: China | F88: Shanghai | G88: Corporate | H88: Retail | I88: K. Singh | J88: Components | K88: CMP-8196 | L88: 1366.48 | M88: 1678.14 | N88: 0.154 | O88: 10
A89: ORD-2025-863978 | B89: 45876 | C89: 45888 | D89: Africa | E89: Kenya | F89: Nakuru | G89: Corporate | I89: M. Rossi | J89: Components | K89: CMP-2854 | L89: 601.51 | M89: 679.35 | N89: 0.188 | O89: 3
A90: ORD-2024-604471 | B90: 45312 | C90: 45316 | D90: Asia | E90: India | F90: Delhi | G90: Consumer | H90: Direct | I90: C. Otieno | J90: Monitors | K90: MON-8973 | L90: 523.7 | M90: 1109.92 | N90: 0.03 | O90: 11
A91: ORD-2023-258768 | B91: 45106 | C91: 45109 | D91: Asia | E91: Japan | F91: Nagoya | G91: Education | H91: Marketplace | I91: F. Müller | J91: Monitors | K91: MON-2990 | L91: 55.65 | M91: 83.57 | N91: 0.066 | O91: 8
A92: ORD-2025-626047 | B92: 45775 | C92: 45792 | D92: Asia | E92: Japan | F92: Nagoya | G92: Education | H92: Direct | I92: N. Brown | J92: Networking | K92: NET-1966 | L92: 691.19 | M92: 1284.3 | N92: 0.074 | O92: 7
A93: ORD-2025-526752 | B93: 45817 | C93: 45833 | D93: Asia | E93: India | F93: Hyderabad | G93: Enterprise | H93: Distributor | I93: M. Rossi | J93: Phones | K93: PHN-3482 | L93: 527.33 | M93: 911.72 | N93: 0.144 | O93: 25
A94: ORD-2023-374486 | B94: 45101 | C94: 45100 | D94: Americas | E94: Brazil | F94: Rio de Janeiro | G94: Non-Profit | H94: Retail | I94: E. Garcia | J94: Printers | K94: PRN-6490 | L94: 804.01 | M94: 1405.07 | N94: 0.096 | O94: 8
A95: ORD-2024-997336 | B95: 45569 | C95: 45598 | D95: Africa | E95: Nigeria | F95: Abuja | G95: Corporate | H95: Distributor | I95: F. Müller | J95: Accessories | K95: ACC-9038 | L95: 412.09 | M95: 968.94 | N95: 0.099 | O95: 23
A96: ORD-2025-725646 | B96: 45910 | C96: 45930 | D96: Africa | E96: Kenya | F96: Mombasa | G96: Corporate | H96: Direct | I96: L. Okafor | J96: Phones | K96: PHN-6954 | L96: 1009.48 | M96: 1088.81 | N96: 0.16 | O96: 6
A97: ORD-2023-868734 | B97: 45022 | C97: 45043 | D97: Europe | E97: United Kingdom | F97: Manchester | G97: Enterprise | H97: Distributor | I97: I. Johnson | J97: Printers | K97: PRN-8970 | L97: 1084.79 | M97: 2484.99 | N97: 0.034 | O97: 18
A98: ORD-2025-262491 | B98: 45870 | C98: 45885 | D98: Asia | E98: India | G98: Enterprise | H98: Direct | I98: O. Wang | J98: Monitors | K98: MON-1822 | L98: 24.44 | M98: 28.69 | N98: 0.146 | O98: 6
A99: ORD-2024-638884 | B99: 45440 | C99: 45438 | D99: Africa | E99: Nigeria | F99: Abuja | G99: Enterprise | H99: Online | I99: F. Müller | J99: Accessories | K99: ACC-5177 | L99: 1227.08 | M99: 1896.62 | N99: 0 | O99: 18
A100: ORD-2025-541501 | B100: 45860 | C100: 45887 | D100: Asia | E100: China | F100: Shenzhen | G100: Non-Profit | H100: Marketplace | I100: M. Rossi | J100: Networking | K100: NET-1804 | L100: 547.32 | M100: 419.17 | N100: 0.092 | O100: 14
A101: ORD-2023-422918 | B101: 44985 | C101: 45005 | D101: Europe | E101: Germany | F101: Berlin | G101: Small Business | H101: Direct | I101: H. Kim | J101: Laptops | K101: LAP-3679 | L101: 1200.78 | M101: 2001.17 | N101: 0.292 | O101: 18
A102: ORD-2025-328504 | B102: 45684 | C102: 45703 | D102: Asia | E102: China | F102: Shenzhen | G102: Non-Profit | H102: Direct | I102: L. Okafor | J102: Phones | K102: PHN-8368 | L102: 1253.22 | M102: 3104.71 | N102: 0 | O102: 17
A103: ORD-2024-851883 | B103: 45304 | C103: 45313 | D103: Asia | E103: India | F103: Mumbai | G103: Enterprise | H103: Marketplace | I103: J. Njeri | J103: Components | K103: CMP-8141 | L103: 313.6 | M103: 334.28 | N103: 0.14 | O103: 22
A104: ORD-2025-662997 | B104: 45747 | C104: 45751 | D104: Africa | E104: Kenya | F104: Nakuru | G104: Corporate | H104: Direct | I104: C. Otieno | J104: Laptops | K104: LAP-7136 | L104: 862.08 | M104: 1952.83 | N104: 0 | O104: 7
A105: ORD-2024-478165 | B105: 45631 | C105: 45654 | D105: Americas | E105: Canada | F105: Vancouver | G105: Corporate | H105: Direct | I105: F. Müller | J105: Accessories | K105: ACC-2386 | L105: 107.03 | M105: 242.29 | N105: 0.18 | O105: 30
A106: ORD-2024-771210 | B106: 45549 | C106: 45570 | D106: Asia | E106: China | F106: Shanghai | G106: Small Business | H106: Online | I106: H. Kim | J106: Laptops | K106: LAP-5150 | L106: 1405.56 | M106: 2968.87 | N106: 0.169 | O106: 5
A107: ORD-2024-155337 | B107: 45433 | C107: 45439 | D107: Africa | E107: South Africa | F107: Johannesburg | G107: Non-Profit | H107: Online | I107: M. Rossi | J107: Components | K107: CMP-8101 | L107: 1157.51 | M107: 1394.3 | N107: 0.278 | O107: 12
A108: ORD-2023-251563 | B108: 45057 | C108: 45084 | D108: Africa | E108: Kenya | F108: Mombasa | G108: Corporate | H108: Online | I108: J. Njeri | J108: Phones | K108: PHN-8970 | L108: 12.85 | M108: 15.41 | N108: 0.137 | O108: 39
A109: ORD-2024-286833 | B109: 45518 | C109: 45539 | D109: Europe | E109: United Kingdom | F109: Manchester | G109: Non-Profit | H109: Online | I109: J. Njeri | J109: Phones | K109: PHN-2341 | L109: 1138.8 | M109: 2250.81 | N109: 0.123 | O109: 12
A110: ORD-2024-792558 | B110: 45581 | C110: 45604 | D110: Asia | E110: Japan | F110: Osaka | G110: Small Business | H110: Retail | I110: J. Njeri | J110: Networking | K110: NET-6387 | L110: 82.14 | M110: 166.04 | N110: 0 | O110: 10
... A121: ORD-2025-956101 | B121: 45847 | C121: 45856 | D121: Americas | E121: Canada | F121: Vancouver | G121: Education | H121: Distributor | I121: I. Johnson | J121: Laptops | K121: LAP-2218 | L121: 57.96 | M121: 88.51 | N121: 0.043 | O121: 7
A122: ORD-2025-184082 | B122: 45827 | C122: 45850 | D122: Europe | E122: United Kingdom | G122: Non-Profit | H122: Direct | J122: Networking | K122: NET-6370 | L122: 801.24 | M122: 1959.09 | N122: 0.123 | O122: 23
A123: ORD-2023-576840 | B123: 45249 | C123: 45273 | D123: Europe | E123: France | F123: Lyon | G123: Non-Profit | H123: Direct | I123: H. Kim | J123: Monitors | K123: MON-3745 | L123: 1297.42 | M123: 2742.97 | N123: 0.069 | O123: 9
A124: ORD-2023-178249 | B124: 45289 | C124: 45311 | D124: Africa | E124: Kenya | F124: Kisumu | G124: Corporate | H124: Direct | I124: L. Okafor | J124: Phones | K124: PHN-7924 | L124: 1395.49 | M124: 1679.42 | N124: 0.203 | O124: 12
A125: ORD-2024-588972 | B125: 45598 | C125: 45625 | D125: Americas | E125: Brazil | F125: Brasília | G125: Small Business | H125: Direct | I125: I. Johnson | J125: Networking | K125: NET-8561 | L125: 1363.51 | M125: 1433.9 | N125: 0.057 | O125: 8
A126: ORD-2023-603238 | B126: 45159 | C126: 45173 | D126: Americas | E126: Canada | F126: Montreal | G126: Education | H126: Distributor | I126: F. Müller | J126: Components | K126: CMP-2136 | L126: 178.19 | M126: 284.43 | N126: 0.089 | O126: 8
A127: ORD-2023-883066 | B127: 45150 | C127: 45175 | D127: Asia | E127: China | F127: Shanghai | G127: Small Business | H127: Retail | I127: B. Chen | J127: Components | K127: CMP-6352 | L127: 950.77 | M127: 694.78 | N127: 0.084 | O127: 14
A128: ORD-2024-584090 | B128: 45450 | C128: 45469 | D128: Europe | E128: Germany | F128: Berlin | G128: Non-Profit | H128: Marketplace | I128: M. Rossi | J128: Components | K128: CMP-2040 | L128: 1064.32 | M128: 1848.39 | N128: 0.073 | O128: 38
A129: ORD-2025-537785 | B129: 45874 | C129: 45883 | D129: Europe | E129: United Kingdom | F129: London | G129: Non-Profit | H129: Direct | I129: E. Garcia | J129: Components | K129: CMP-6346 | L129: 41.76 | M129: 45.19 | N129: 0.179 | O129: 23
A130: ORD-2024-605518 | B130: 45442 | C130: 45456 | D130: Americas | E130: USA | F130: San Francisco | G130: Small Business | H130: Retail | I130: F. Müller | J130: Phones | K130: PHN-4356 | L130: 157.78 | M130: 361.1 | N130: 0.187 | O130: 9
A131: ORD-2023-521818 | B131: 44948 | C131: 44956 | D131: Americas | E131: USA | F131: San Francisco | G131: Small Business | H131: Online | I131: A. Patel | J131: Networking | K131: NET-4155 | L131: 413.52 | M131: 1004.34 | N131: 0.111 | O131: 18
A132: ORD-2025-650719 | B132: 45700 | C132: 45716 | D132: Americas | E132: Brazil | F132: São Paulo | G132: Non-Profit | H132: Direct | I132: B. Chen | J132: Monitors | K132: MON-5179 | L132: 414.95 | M132: 1027.73 | N132: 0.063 | O132: 8
A133: ORD-2025-501927 | B133: 45719 | C133: 45740 | D133: Africa | E133: Nigeria | F133: Abuja | G133: Enterprise | H133: Direct | I133: H. Kim | J133: Accessories | K133: ACC-4056 | L133: 555.95 | M133: 468.09 | N133: 0.142 | O133: 11
A134: ORD-2023-430904 | B134: 44953 | C134: 44957 | D134: Europe | E134: United Kingdom | F134: Manchester | G134: Enterprise | H134: Online | I134: N. Brown | J134: Laptops | K134: LAP-9782 | L134: 941.2 | M134: 668.02 | N134: 0.22 | O134: 16
... A187: ORD-2023-399631 | B187: 45099 | C187: 45128 | D187: Europe | E187: France | F187: Lyon | G187: Corporate | H187: Retail | I187: J. Njeri | J187: Accessories | K187: ACC-3385 | L187: 734.34 | M187: 887.9 | N187: 0.025 | O187: 12
A188: ORD-2025-542939 | B188: 45670 | C188: 45696 | D188: Europe | E188: France | F188: Paris | G188: Non-Profit | I188: E. Garcia | J188: Monitors | K188: MON-1593 | L188: 594.74 | M188: 1020.69 | N188: 0.211 | O188: 6
A189: ORD-2023-521818 | B189: 44955 | C189: 44985 | D189: Asia | E189: India | F189: Bengaluru | G189: Non-Profit | H189: Retail | I189: B. Chen | J189: Accessories | K189: ACC-4631 | L189: 1262.1 | M189: 1395.53 | N189: 0.233 | O189: 25
A190: ORD-2023-825836 | B190: 45126 | C190: 45138 | D190: Americas | E190: Brazil | F190: Rio de Janeiro | G190: Corporate | H190: Retail | I190: C. Otieno | J190: Monitors | K190: MON-7869 | L190: 1334.64 | M190: 2273.42 | N190: 0.118 | O190: 14
A191: ORD-2024-503082 | B191: 45431 | C191: 45451 | D191: Americas | E191: Brazil | F191: Brasília | G191: Small Business | H191: Retail | I191: E. Garcia | J191: Monitors | K191: MON-4271 | L191: 1075.9 | M191: 1242.15 | N191: 0.012 | O191: 7
A192: ORD-2024-760799 | B192: 45325 | C192: 45341 | D192: Asia | E192: China | F192: Shenzhen | G192: Small Business | H192: Online | I192: H. Kim | J192: Laptops | K192: LAP-5531 | L192: 993.75 | M192: 1310.29 | N192: 0.215 | O192: 19
A193: ORD-2023-197661 | B193: 45146 | C193: 45160 | D193: Europe | E193: United Kingdom | F193: Birmingham | G193: Non-Profit | H193: Direct | I193: N. Brown | J193: Monitors | K193: MON-7511 | L193: 446.69 | M193: 967.25 | N193: 0.094 | O193: 10
A194: ORD-2024-212990 | B194: 45516 | C194: 45538 | D194: Americas | E194: USA | F194: Austin | G194: Consumer | H194: Distributor | I194: I. Johnson | J194: Laptops | K194: LAP-7979 | L194: 797.8 | M194: 886.22 | N194: 0.236 | O194: 36
A195: ORD-2023-925146 | B195: 45214 | C195: 45243 | D195: Asia | E195: China | F195: Shenzhen | G195: Non-Profit | H195: Distributor | I195: J. Njeri | J195: Printers | K195: PRN-4983 | L195: 986.44 | M195: 790.61 | N195: 0.072 | O195: 6
A196: ORD-2023-177794 | B196: 45050 | C196: 45072 | D196: Americas | E196: USA | F196: San Francisco | G196: Enterprise | H196: Online | I196: J. Njeri | J196: Networking | K196: NET-5941 | L196: 249.71 | M196: 361.33 | N196: 0.094 | O196: 12
A197: ORD-2024-444710 | B197: 45557 | C197: 45566 | D197: Americas | E197: Brazil | F197: São Paulo | G197: Non-Profit | H197: Online | I197: K. Singh | J197: Monitors | K197: MON-6341 | L197: 1378.8 | M197: 1952.04 | N197: 0.159 | O197: 19
A198: ORD-2024-668926 | B198: 45588 | C198: 45610 | D198: Asia | E198: Japan | F198: Osaka | G198: Non-Profit | H198: Direct | I198: B. Chen | J198: Phones | K198: PHN-9789 | L198: 1406.4 | M198: 1564.76 | N198: 0.185 | O198: 17
A199: ORD-2024-968374 | B199: 45333 | C199: 45354 | D199: Africa | E199: Kenya | F199: Kisumu | G199: Enterprise | H199: Online | I199: B. Chen | J199: Phones | K199: PHN-5082 | L199: 516.86 | M199: 852.54 | N199: 0.051 | O199: 14
A200: ORD-2023-575584 | B200: 44956 | C200: 44978 | D200: Europe | E200: Germany | F200: Munich | G200: Small Business | H200: Marketplace | I200: G. Dubois | J200: Networking | K200: NET-3460 | L200: 1142.88 | M200: 1465.29 | N200: 0.186 | O200: 7
... A236: ORD-2023-946143 | B236: 44999 | C236: 45015 | D236: Africa | E236: South Africa | F236: Cape Town | G236: Consumer | H236: Distributor | I236: K. Singh | J236: Components | K236: CMP-8230 | L236: 1309.77 | M236: 1589.07 | N236: 0.102 | O236: 10
A237: ORD-2024-281211 | B237: 45302 | C237: 45324 | D237: Asia | E237: Japan | F237: Nagoya | G237: Small Business | H237: Online | J237: Printers | K237: PRN-7816 | L237: 1237.68 | M237: 1432.8 | N237: 0.068 | O237: 13
A238: ORD-2024-805860 | B238: 45548 | C238: 45567 | D238: Africa | E238: Kenya | F238: Mombasa | G238: Small Business | H238: Retail | I238: M. Rossi | J238: Phones | K238: PHN-8804 | L238: 1338.99 | M238: 1765.76 | N238: 0.126 | O238: 24
A239: ORD-2025-132174 | B239: 45855 | C239: 45861 | D239: Americas | E239: Canada | F239: Vancouver | G239: Consumer | H239: Online | I239: H. Kim | J239: Components | K239: CMP-8851 | L239: 1364.89 | M239: 2757.54 | N239: 0.172 | O239: 61
A240: ORD-2023-964434 | B240: 45258 | C240: 45267 | D240: Asia | E240: India | F240: Delhi | G240: Enterprise | H240: Marketplace | I240: L. Okafor | J240: Phones | K240: PHN-2447 | L240: 699.33 | M240: 873.75 | N240: 0.235 | O240: 10
A241: ORD-2024-897622 | B241: 45381 | C241: 45406 | D241: Americas | E241: USA | F241: Austin | G241: Non-Profit | H241: Online | I241: G. Dubois | J241: Laptops | K241: LAP-2846 | L241: 160.82 | M241: 258.52 | N241: 0.13 | O241: 17
A242: ORD-2023-517216 | B242: 45188 | C242: 45207 | D242: Asia | E242: India | F242: Bengaluru | G242: Education | H242: Direct | I242: J. Njeri | J242: Printers | K242: PRN-5005 | L242: 385.32 | M242: 606.76 | N242: 0.086 | O242: 8
A243: ORD-2025-509940 | B243: 45793 | C243: 45804 | D243: Asia | E243: China | F243: Beijing | G243: Enterprise | H243: Online | I243: F. Müller | J243: Phones | K243: PHN-3800 | L243: 918.12 | M243: 1337.69 | N243: 0.095 | O243: 8
A244: ORD-2025-646342 | B244: 45871 | C244: 45877 | D244: Asia | E244: Japan | F244: Osaka | G244: Consumer | H244: Direct | I244: N. Brown | J244: Laptops | K244: LAP-4828 | L244: 1225.94 | M244: 1793.08 | N244: 0.136 | O244: 22
A245: ORD-2024-866535 | B245: 45630 | C245: 45638 | D245: Europe | E245: Germany | F245: Frankfurt | G245: Enterprise | H245: Marketplace | I245: B. Chen | J245: Printers | K245: PRN-5492 | L245: 72.06 | M245: 122.74 | N245: 0.238 | O245: 8
A246: ORD-2023-747341 | B246: 45035 | C246: 45044 | D246: Americas | E246: Brazil | F246: Rio de Janeiro | G246: Corporate | H246: Distributor | I246: M. Rossi | J246: Phones | K246: PHN-7132 | L246: 1013.54 | M246: 927.93 | N246: 0.175 | O246: 16
...

Sheet Brief
A1: Assignment
A2: Excel Mastery Assignment: Sales Operations & Analytics
A4: Overview:
A5: You are an analyst for a multi-regional electronics distributor. The 'Data' sheet contains 632 rows and 15 columns of transactional data with intentional data-quality issues.
A6: Your job is to clean, enrich, analyze, and present insights via a dynamic dashboard.
A8: Part A — Data Cleaning & Preparation:
A9: 1) Create a staging table where you:
A10: • Remove exact duplicate rows (define and document your duplicate criteria).
A11: • Fix data types (dates as Dates, numeric fields as numbers).
A12: • Handle missing values for City, Salesperson, and Channel using reasonable business logic (document your approach).
A13: • Flag and correct suspicious UnitPrice values (e.g., negative prices) and discounts (e.g., > 30%).
A14: • Ensure RequiredDate is not earlier than OrderDate; where it is, impute a corrected RequiredDate (explain your rule).
... A67: 15) Ensure your dashboard responds to slicers without broken references.

Sheet 1. Staging Table
A1: OrderID | B1: OrderDate | C1: Month Of OrderDate | D1: Month | E1: Quarter | F1: RequiredDate | G1: Corrected Required Date | H1: LeadTime Days | I1: On-Time | J1: Region | K1: Country | L1: City | M1: CustomerSegment | N1: Channel | O1: Salesperson | P1: ProductCategory | Q1: SKU | R1: UnitCost | S1: UnitPrice | T1: Corrected Unit price | U1: UnitCost Inflation Factor | V1: Derived Price Band | W1: DiscountPct | X1: DiscountPct> 20% | Y1: Global DiscountCap | Z1: Quantity | AA1: Quantity Uplift | AB1: GrossRevenue | AC1: WhatIfRevenue | AD1: CostOfGoods | AE1: GrossProfit | AF1: WhatIfProfit | AG1: MarginPct
A2: ORD-2024-275203 | B2: 45362 | C2: =MONTH(B2) -> 3 | D2: =B2 -> 45362 | E2: =IF(AND(MONTH(B2)>=1,MONTH(B2)<=3),"Quarter 1",IF(AND(MONTH(B2)>=4,MONTH(B2)<=6),"Quarter 2",IF(AND(MONTH(B2)>=7,MONTH(B2)<=9),"Quarter 3",IF(AND(MONTH(B2)>=10,MONTH(B2)<=12),"Quarter 4")))) -> Quarter 1 | F2: 45388 | G2: =IF(B2>F2,B2+7,F2) -> 45388 | H2: =G2-B2 -> 26 | I2: =IF(H2<=7,"Ontime","Delayed ") -> Delayed | J2: Africa | K2: Kenya | L2: Kisumu | M2: Corporate | N2: Retail | O2: C. Otieno | P2: Components | Q2: CMP-8270 | R2: 279.24 | S2: 608.9 | T2: =IF(S2<=0,R2,S2) -> 608.9 | U2: =(1+'10. Whatif Control pannel'!$B$6)*T2 -> 681.968 | V2: =IF(T2<=_xlfn.PERCENTILE.INC(T2:T633,33%),"Low",IF(T2<=_xlfn.PERCENTILE.INC(T2:T633,67%),"Medium","High")) -> Low | W2: 0.112 | X2: =IF(W2>0.2,"High Discount","Okay") -> Okay | Y2: =IF(W2<=0.25,W2,'10. Whatif Control pannel'!$B$2) -> 0.112 | Z2: 9 | AA2: =(1+'10. Whatif Control pannel'!$B$10)*Z2 -> 10.8 | AB2: =T2*Z2*(1-W2) -> 4866.3288 | AC2: =U2*AA2*(1-Y2) -> 6540.3459 | AD2: =R2*Z2 -> 2513.16 | AE2: =AB2-AD2 -> 2353.1688 | AF2: =AC2-AD2 -> 4027.1859 | AG2: =IF(AB2=0,0,AE2/AB2) -> 0.48356141
A3: ORD-2024-358795 | B3: 45588 | C3: =MONTH(B3) -> 10 | D3: =B3 -> 45588 | E3: =IF(AND(MONTH(B3)>=1,MONTH(B3)<=3),"Quarter 1",IF(AND(MONTH(B3)>=4,MONTH(B3)<=6),"Quarter 2",IF(AND(MONTH(B3)>=7,MONTH(B3)<=9),"Quarter 3",IF(AND(MONTH(B3)>=10,MONTH(B3)<=12),"Quarter 4")))) -> Quarter 4 | F3: 45587 | G3: =IF(B3>F3,B3+7,F3) -> 45595 | H3: =G3-B3 -> 7 | I3: =IF(H3<=7,"Ontime","Delayed ") -> Ontime | J3: Africa | K3: Nigeria | L3: Port Harcourt | M3: Education | N3: Online | O3: J. Njeri | P3: Printers | Q3: PRN-9322 | R3: 1084.39 | S3: 759.33 | T3: =IF(S3<=0,R3,S3) -> 759.33 | U3: =(1+'10. Whatif Control pannel'!$B$6)*T3 -> 850.4496 | V3: =IF(T3<=_xlfn.PERCENTILE.INC(T3:T634,33%),"Low",IF(T3<=_xlfn.PERCENTILE.INC(T3:T634,67%),"Medium","High")) -> Low | W3: 0.237 | X3: =IF(W3>0.2,"High Discount","Okay") -> High Discount | Y3: =IF(W3<=0.25,W3,'10. Whatif Control pannel'!$B$2) -> 0.237 | Z3: 31 | AA3: =(1+'10. Whatif Control pannel'!$B$10)*Z3 -> 37.2 | AB3: =T3*Z3*(1-W3) -> 17960.432 | AC3: =U3*AA3*(1-Y3) -> 24138.821 | AD3: =R3*Z3 -> 33616.09 | AE3: =AB3-AD3 -> -15655.658 | AF3: =AC3-AD3 -> -9477.2687 | AG3: =IF(AB3=0,0,AE3/AB3) -> -0.87167486
A4: ORD-2023-373538 | B4: 44985 | C4: =MONTH(B4) -> 2 | D4: =B4 -> 44985 | E4: =IF(AND(MONTH(B4)>=1,MONTH(B4)<=3),"Quarter 1",IF(AND(MONTH(B4)>=4,MONTH(B4)<=6),"Quarter 2",IF(AND(MONTH(B4)>=7,MONTH(B4)<=9),"Quarter 3",IF(AND(MONTH(B4)>=10,MONTH(B4)<=12),"Quarter 4")))) -> Quarter 1 | F4: 45010 | G4: =IF(B4>F4,B4+7,F4) -> 45010 | H4: =G4-B4 -> 25 | I4: =IF(H4<=7,"Ontime","Delayed ") -> Delayed | J4: Africa | K4: Kenya | L4: Nairobi | M4: Corporate | N4: Retail | O4: I. Johnson | P4: Networking | Q4: NET-9666 | R4: 1460.76 | S4: -30.66 | T4: =IF(S4<=0,R4,S4) -> 1460.76 | U4: =(1+'10. Whatif Control pannel'!$B$6)*T4 -> 1636.0512 | V4: =IF(T4<=_xlfn.PERCENTILE.INC(T4:T635,33%),"Low",IF(T4<=_xlfn.PERCENTILE.INC(T4:T635,67%),"Medium","High")) -> Medium | W4: 0.131 | X4: =IF(W4>0.2,"High Discount","Okay") -> Okay | Y4: =IF(W4<=0.25,W4,'10. Whatif Control pannel'!$B$2) -> 0.131 | Z4: 12 | AA4: =(1+'10. Whatif Control pannel'!$B$10)*Z4 -> 14.4 | AB4: =T4*Z4*(1-W4) -> 15232.805 | AC4: =U4*AA4*(1-Y4) -> 20472.89 | AD4: =R4*Z4 -> 17529.12 | AE4: =AB4-AD4 -> -2296.3147 | AF4: =AC4-AD4 -> 2943.7703 | AG4: =IF(AB4=0,0,AE4/AB4) -> -0.15074799
A5: ORD-2025-168148 | B5: 45745 | C5: =MONTH(B5) -> 3 | D5: =B5 -> 45745 | E5: =IF(AND(MONTH(B5)>=1,MONTH(B5)<=3),"Quarter 1",IF(AND(MONTH(B5)>=4,MONTH(B5)<=6),"Quarter 2",IF(AND(MONTH(B5)>=7,MONTH(B5)<=9),"Quarter 3",IF(AND(MONTH(B5)>=10,MONTH(B5)<=12),"Quarter 4")))) -> Quarter 1 | F5: 45749 | G5: =IF(B5>F5,B5+7,F5) -> 45749 | H5: =G5-B5 -> 4 | I5: =IF(H5<=7,"Ontime","Delayed ") -> Ontime | J5: Africa | K5: Nigeria | L5: Lagos | M5: Non-Profit | N5: Marketplace | O5: G. Dubois | P5: Phones | Q5: PHN-4556 | R5: 259.93 | S5: 255.94 | T5: =IF(S5<=0,R5,S5) -> 255.94 | U5: =(1+'10. Whatif Control pannel'!$B$6)*T5 -> 286.6528 | V5: =IF(T5<=_xlfn.PERCENTILE.INC(T5:T636,33%),"Low",IF(T5<=_xlfn.PERCENTILE.INC(T5:T636,67%),"Medium","High")) -> Low | W5: 0.072 | X5: =IF(W5>0.2,"High Discount","Okay") -> Okay | Y5: =IF(W5<=0.25,W5,'10. Whatif Control pannel'!$B$2) -> 0.072 | Z5: 22 | AA5: =(1+'10. Whatif Control pannel'!$B$10)*Z5 -> 26.4 | AB5: =T5*Z5*(1-W5) -> 5225.271 | AC5: =U5*AA5*(1-Y5) -> 7022.7643 | AD5: =R5*Z5 -> 5718.46 | AE5: =AB5-AD5 -> -493.18896 | AF5: =AC5-AD5 -> 1304.3043 | AG5: =IF(AB5=0,0,AE5/AB5) -> -0.094385335
A6: ORD-2023-824839 | B6: 45266 | C6: =MONTH(B6) -> 12 | D6: =B6 -> 45266 | E6: =IF(AND(MONTH(B6)>=1,MONTH(B6)<=3),"Quarter 1",IF(AND(MONTH(B6)>=4,MONTH(B6)<=6),"Quarter 2",IF(AND(MONTH(B6)>=7,MONTH(B6)<=9),"Quarter 3",IF(AND(MONTH(B6)>=10,MONTH(B6)<=12),"Quarter 4")))) -> Quarter 4 | F6: 45291 | G6: =IF(B6>F6,B6+7,F6) -> 45291 | H6: =G6-B6 -> 25 | I6: =IF(H6<=7,"Ontime","Delayed ") -> Delayed | J6: Asia | K6: Japan | L6: Osaka | M6: Consumer | N6: Retail | O6: L. Okafor | P6: Printers | Q6: PRN-8041 | R6: 663.03 | S6: 813.51 | T6: =IF(S6<=0,R6,S6) -> 813.51 | U6: =(1+'10. Whatif Control pannel'!$B$6)*T6 -> 911.1312 | V6: =IF(T6<=_xlfn.PERCENTILE.INC(T6:T637,33%),"Low",IF(T6<=_xlfn.PERCENTILE.INC(T6:T637,67%),"Medium","High")) -> Low | W6: 0.102 | X6: =IF(W6>0.2,"High Discount","Okay") -> Okay | Y6: =IF(W6<=0.25,W6,'10. Whatif Control pannel'!$B$2) -> 0.102 | Z6: 15 | AA6: =(1+'10. Whatif Control pannel'!$B$10)*Z6 -> 18 | AB6: =T6*Z6*(1-W6) -> 10957.98 | AC6: =U6*AA6*(1-Y6) -> 14727.525 | AD6: =R6*Z6 -> 9945.45 | AE6: =AB6-AD6 -> 1012.5297 | AF6: =AC6-AD6 -> 4782.0747 | AG6: =IF(AB6=0,0,AE6/AB6) -> 0.092401129
A7: ORD-2023-723587 | B7: 44928 | C7: =MONTH(B7) -> 1 | D7: =B7 -> 44928 | E7: =IF(AND(MONTH(B7)>=1,MONTH(B7)<=3),"Quarter 1",IF(AND(MONTH(B7)>=4,MONTH(B7)<=6),"Quarter 2",IF(AND(MONTH(B7)>=7,MONTH(B7)<=9),"Quarter 3",IF(AND(MONTH(B7)>=10,MONTH(B7)<=12),"Quarter 4")))) -> Quarter 1 | F7: 44931 | G7: =IF(B7>F7,B7+7,F7) -> 44931 | H7: =G7-B7 -> 3 | I7: =IF(H7<=7,"Ontime","Delayed ") -> Ontime | J7: Americas | K7: Canada | L7: Toronto | M7: Corporate | N7: Distributor | O7: B. Chen | P7: Laptops | Q7: LAP-8555 | R7: 315.87 | S7: 591.68 | T7: =IF(S7<=0,R7,S7) -> 591.68 | U7: =(1+'10. Whatif Control pannel'!$B$6)*T7 -> 662.6816 | V7: =IF(T7<=_xlfn.PERCENTILE.INC(T7:T638,33%),"Low",IF(T7<=_xlfn.PERCENTILE.INC(T7:T638,67%),"Medium","High")) -> Low | W7: 0 | X7: =IF(W7>0.2,"High Discount","Okay") -> Okay | Y7: =IF(W7<=0.25,W7,'10. Whatif Control pannel'!$B$2) -> 0 | Z7: 7 | AA7: =(1+'10. Whatif Control pannel'!$B$10)*Z7 -> 8.4 | AB7: =T7*Z7*(1-W7) -> 4141.76 | AC7: =U7*AA7*(1-Y7) -> 5566.5254 | AD7: =R7*Z7 -> 2211.09 | AE7: =AB7-AD7 -> 1930.67 | AF7: =AC7-AD7 -> 3355.4354 | AG7: =IF(AB7=0,0,AE7/AB7) -> 0.46614724
A8: ORD-2024-336584 | B8: 45653 | C8: =MONTH(B8) -> 12 | D8: =B8 -> 45653 | E8: =IF(AND(MONTH(B8)>=1,MONTH(B8)<=3),"Quarter 1",IF(AND(MONTH(B8)>=4,MONTH(B8)<=6),"Quarter 2",IF(AND(MONTH(B8)>=7,MONTH(B8)<=9),"Quarter 3",IF(AND(MONTH(B8)>=10,MONTH(B8)<=12),"Quarter 4")))) -> Quarter 4 | F8: 45671 | G8: =IF(B8>F8,B8+7,F8) -> 45671 | H8: =G8-B8 -> 18 | I8: =IF(H8<=7,"Ontime","Delayed ") -> Delayed | J8: Asia | K8: India | L8: Bengaluru | M8: Small Business | N8: Marketplace | O8: E. Garcia | P8: Monitors | Q8: MON-8629 | R8: 586.07 | S8: 845.97 | T8: =IF(S8<=0,R8,S8) -> 845.97 | U8: =(1+'10. Whatif Control pannel'!$B$6)*T8 -> 947.4864 | V8: =IF(T8<=_xlfn.PERCENTILE.INC(T8:T639,33%),"Low",IF(T8<=_xlfn.PERCENTILE.INC(T8:T639,67%),"Medium","High")) -> Medium | W8: 0.147 | X8: =IF(W8>0.2,"High Discount","Okay") -> Okay | Y8: =IF(W8<=0.25,W8,'10. Whatif Control pannel'!$B$2) -> 0.147 | Z8: 4 | AA8: =(1+'10. Whatif Control pannel'!$B$10)*Z8 -> 4.8 | AB8: =T8*Z8*(1-W8) -> 2886.4496 | AC8: =U8*AA8*(1-Y8) -> 3879.3883 | AD8: =R8*Z8 -> 2344.28 | AE8: =AB8-AD8 -> 542.16964 | AF8: =AC8-AD8 -> 1535.1083 | AG8: =IF(AB8=0,0,AE8/AB8) -> 0.1878327
A9: ORD-2023-112666 | B9: 44941 | C9: =MONTH(B9) -> 1 | D9: =B9 -> 44941 | E9: =IF(AND(MONTH(B9)>=1,MONTH(B9)<=3),"Quarter 1",IF(AND(MONTH(B9)>=4,MONTH(B9)<=6),"Quarter 2",IF(AND(MONTH(B9)>=7,MONTH(B9)<=9),"Quarter 3",IF(AND(MONTH(B9)>=10,MONTH(B9)<=12),"Quarter 4")))) -> Quarter 1 | F9: 44939 | G9: =IF(B9>F9,B9+7,F9) -> 44948 | H9: =G9-B9 -> 7 | I9: =IF(H9<=7,"Ontime","Delayed ") -> Ontime | J9: Africa | K9: Nigeria | L9: Abuja | M9: Education | N9: Online | O9: O. Wang | P9: Printers | Q9: PRN-6276 | R9: 28.38 | S9: 47.22 | T9: =IF(S9<=0,R9,S9) -> 47.22 | U9: =(1+'10. Whatif Control pannel'!$B$6)*T9 -> 52.8864 | V9: =IF(T9<=_xlfn.PERCENTILE.INC(T9:T640,33%),"Low",IF(T9<=_xlfn.PERCENTILE.INC(T9:T640,67%),"Medium","High")) -> Low | W9: 0.194 | X9: =IF(W9>0.2,"High Discount","Okay") -> Okay | Y9: =IF(W9<=0.25,W9,'10. Whatif Control pannel'!$B$2) -> 0.194 | Z9: 18 | AA9: =(1+'10. Whatif Control pannel'!$B$10)*Z9 -> 21.6 | AB9: =T9*Z9*(1-W9) -> 685.06776 | AC9: =U9*AA9*(1-Y9) -> 920.73107 | AD9: =R9*Z9 -> 510.84 | AE9: =AB9-AD9 -> 174.22776 | AF9: =AC9-AD9 -> 409.89107 | AG9: =IF(AB9=0,0,AE9/AB9) -> 0.25432194
A10: ORD-2024-589570 | B10: 45416 | C10: =MONTH(B10) -> 5 | D10: =B10 -> 45416 | E10: =IF(AND(MONTH(B10)>=1,MONTH(B10)<=3),"Quarter 1",IF(AND(MONTH(B10)>=4,MONTH(B10)<=6),"Quarter 2",IF(AND(MONTH(B10)>=7,MONTH(B10)<=9),"Quarter 3",IF(AND(MONTH(B10)>=10,MONTH(B10)<=12),"Quarter 4")))) -> Quarter 2 | F10: 45441 | G10: =IF(B10>F10,B10+7,F10) -> 45441 | H10: =G10-B10 -> 25 | I10: =IF(H10<=7,"Ontime","Delayed ") -> Delayed | J10: Africa | K10: Nigeria | L10: Abuja | M10: Non-Profit | N10: Marketplace | O10: O. Wang | P10: Monitors | Q10: MON-6892 | R10: 1295.34 | S10: 2530.81 | T10: =IF(S10<=0,R10,S10) -> 2530.81 | U10: =(1+'10. Whatif Control pannel'!$B$6)*T10 -> 2834.5072 | V10: =IF(T10<=_xlfn.PERCENTILE.INC(T10:T641,33%),"Low",IF(T10<=_xlfn.PERCENTILE.INC(T10:T641,67%),"Medium","High")) -> High | W10: 0.031 | X10: =IF(W10>0.2,"High Discount","Okay") -> Okay | Y10: =IF(W10<=0.25,W10,'10. Whatif Control pannel'!$B$2) -> 0.031 | Z10: 6 | AA10: =(1+'10. Whatif Control pannel'!$B$10)*Z10 -> 7.2 | AB10: =T10*Z10*(1-W10) -> 14714.129 | AC10: =U10*AA10*(1-Y10) -> 19775.79 | AD10: =R10*Z10 -> 7772.04 | AE10: =AB10-AD10 -> 6942.0893 | AF10: =AC10-AD10 -> 12003.75 | AG10: =IF(AB10=0,0,AE10/AB10) -> 0.47179749
A11: ORD-2025-997421 | B11: 45798 | C11: =MONTH(B11) -> 5 | D11: =B11 -> 45798 | E11: =IF(AND(MONTH(B11)>=1,MONTH(B11)<=3),"Quarter 1",IF(AND(MONTH(B11)>=4,MONTH(B11)<=6),"Quarter 2",IF(AND(MONTH(B11)>=7,MONTH(B11)<=9),"Quarter 3",IF(AND(MONTH(B11)>=10,MONTH(B11)<=12),"Quarter 4")))) -> Quarter 2 | F11: 45817 | G11: =IF(B11>F11,B11+7,F11) -> 45817 | H11: =G11-B11 -> 19 | I11: =IF(H11<=7,"Ontime","Delayed ") -> Delayed | J11: Americas | K11: Brazil | L11: São Paulo | M11: Non-Profit | N11: Online | O11: A. Patel | P11: Components | Q11: CMP-3731 | R11: 1331.38 | S11: 2309.56 | T11: =IF(S11<=0,R11,S11) -> 2309.56 | U11: =(1+'10. Whatif Control pannel'!$B$6)*T11 -> 2586.7072 | V11: =IF(T11<=_xlfn.PERCENTILE.INC(T11:T642,33%),"Low",IF(T11<=_xlfn.PERCENTILE.INC(T11:T642,67%),"Medium","High")) -> High | W11: 0.149 | X11: =IF(W11>0.2,"High Discount","Okay") -> Okay | Y11: =IF(W11<=0.25,W11,'10. Whatif Control pannel'!$B$2) -> 0.149 | Z11: 31 | AA11: =(1+'10. Whatif Control pannel'!$B$10)*Z11 -> 37.2 | AB11: =T11*Z11*(1-W11) -> 60928.502 | AC11: =U11*AA11*(1-Y11) -> 81887.907 | AD11: =R11*Z11 -> 41272.78 | AE11: =AB11-AD11 -> 19655.722 | AF11: =AC11-AD11 -> 40615.127 | AG11: =IF(AB11=0,0,AE11/AB11) -> 0.32260308
A12: ORD-2024-210687 | B12: 45319 | C12: =MONTH(B12) -> 1 | D12: =B12 -> 45319 | E12: =IF(AND(MONTH(B12)>=1,MONTH(B12)<=3),"Quarter 1",IF(AND(MONTH(B12)>=4,MONTH(B12)<=6),"Quarter 2",IF(AND(MONTH(B12)>=7,MONTH(B12)<=9),"Quarter 3",IF(AND(MONTH(B12)>=10,MONTH(B12)<=12),"Quarter 4")))) -> Quarter 1 | F12: 45331 | G12: =IF(B12>F12,B12+7,F12) -> 45331 | H12: =G12-B12 -> 12 | I12: =IF(H12<=7,"Ontime","Delayed ") -> Delayed | J12: Europe | K12: Germany | L12: Berlin | M12: Corporate | N12: Online | O12: G. Dubois | P12: Accessories | Q12: ACC-7938 | R12: 644.17 | S12: 700.12 | T12: =IF(S12<=0,R12,S12) -> 700.12 | U12: =(1+'10. Whatif Control pannel'!$B$6)*T12 -> 784.1344 | V12: =IF(T12<=_xlfn.PERCENTILE.INC(T12:T643,33%),"Low",IF(T12<=_xlfn.PERCENTILE.INC(T12:T643,67%),"Medium","High")) -> Low | W12: 0.006 | X12: =IF(W12>0.2,"High Discount","Okay") -> Okay | Y12: =IF(W12<=0.25,W12,'10. Whatif Control pannel'!$B$2) -> 0.006 | Z12: 23 | AA12: =(1+'10. Whatif Control pannel'!$B$10)*Z12 -> 27.6 | AB12: =T12*Z12*(1-W12) -> 16006.143 | AC12: =U12*AA12*(1-Y12) -> 21512.257 | AD12: =R12*Z12 -> 14815.91 | AE12: =AB12-AD12 -> 1190.2334 | AF12: =AC12-AD12 -> 6696.3468 | AG12: =IF(AB12=0,0,AE12/AB12) -> 0.074361038
A13: ORD-2025-515515 | B13: 45660 | C13: =MONTH(B13) -> 1 | D13: =B13 -> 45660 | E13: =IF(AND(MONTH(B13)>=1,MONTH(B13)<=3),"Quarter 1",IF(AND(MONTH(B13)>=4,MONTH(B13)<=6),"Quarter 2",IF(AND(MONTH(B13)>=7,MONTH(B13)<=9),"Quarter 3",IF(AND(MONTH(B13)>=10,MONTH(B13)<=12),"Quarter 4")))) -> Quarter 1 | F13: 45680 | G13: =IF(B13>F13,B13+7,F13) -> 45680 | H13: =G13-B13 -> 20 | I13: =IF(H13<=7,"Ontime","Delayed ") -> Delayed | J13: Asia | K13: Japan | L13: Osaka | M13: Corporate | N13: Distributor | O13: F. Müller | P13: Phones | Q13: PHN-7019 | R13: 908.6 | S13: 691.37 | T13: =IF(S13<=0,R13,S13) -> 691.37 | U13: =(1+'10. Whatif Control pannel'!$B$6)*T13 -> 774.3344 | V13: =IF(T13<=_xlfn.PERCENTILE.INC(T13:T644,33%),"Low",IF(T13<=_xlfn.PERCENTILE.INC(T13:T644,67%),"Medium","High")) -> Low | W13: 0.25 | X13: =IF(W13>0.2,"High Discount","Okay") -> High Discount | Y13: =IF(W13<=0.25,W13,'10. Whatif Control pannel'!$B$2) -> 0.25 | Z13: 20 | AA13: =(1+'10. Whatif Control pannel'!$B$10)*Z13 -> 24 | AB13: =T13*Z13*(1-W13) -> 10370.55 | AC13: =U13*AA13*(1-Y13) -> 13938.019 | AD13: =R13*Z13 -> 18172 | AE13: =AB13-AD13 -> -7801.45 | AF13: =AC13-AD13 -> -4233.9808 | AG13: =IF(AB13=0,0,AE13/AB13) -> -0.75226965
... A633: ORD-2025-728935 | B633: 45716 | C633: =MONTH(B633) -> 2 | D633: =B633 -> 45716 | E633: =IF(AND(MONTH(B633)>=1,MONTH(B633)<=3),"Quarter 1",IF(AND(MONTH(B633)>=4,MONTH(B633)<=6),"Quarter 2",IF(AND(MONTH(B633)>=7,MONTH(B633)<=9),"Quarter 3",IF(AND(MONTH(B633)>=10,MONTH(B633)<=12),"Quarter 4")))) -> Quarter 1 | F633: 45726 | G633: =IF(B633>F633,B633+7,F633) -> 45726 | H633: =G633-B633 -> 10 | I633: =IF(H633<=7,"Ontime","Delayed ") -> Delayed | J633: Asia | K633: Japan | L633: Osaka | M633: Education | N633: Distributor | O633: N. Brown | P633: Laptops | Q633: LAP-3017 | R633: 51.86 | S633: 45.98 | T633: =IF(S633<=0,R633,S633) -> 45.98 | U633: =(1+'10. Whatif Control pannel'!$B$6)*T633 -> 51.4976 | V633: =IF(T633<=_xlfn.PERCENTILE.INC(T633:T1264,33%),"Low",IF(T633<=_xlfn.PERCENTILE.INC(T633:T1264,67%),"Medium","High")) -> Low | W633: 0.173 | X633: =IF(W633>0.2,"High Discount","Okay") -> Okay | Y633: =IF(W633<=0.25,W633,'10. Whatif Control pannel'!$B$2) -> 0.173 | Z633: 7 | AA633: =(1+'10. Whatif Control pannel'!$B$10)*Z633 -> 8.4 | AB633: =T633*Z633*(1-W633) -> 266.17822 | AC633: =U633*AA633*(1-Y633) -> 357.74353 | AD633: =R633*Z633 -> 363.02 | AE633: =AB633-AD633 -> -96.84178 | AF633: =AC633-AD633 -> -5.2764723 | AG633: =IF(AB633=0,0,AE633/AB633) -> -0.36382308
AB637: =SUM(AB2:AB633) -> 11024296 | AC637: =SUM(AC2:AC633) -> 14886303 | AE637: =SUM(AE2:AE633) -> 3496548.5 | AF637: =SUM(AF2:AF633) -> 7358555.4
AD638: =AB637/632 -> 17443.507

Sheet 2. Region Hierachy Pivot Table
A3: Region | B3: Country | C3: City
A4: Africa
B5: Kenya
B6: Nigeria
C7: Abuja
C8: Lagos
C9: Port Harcourt
C10: Unknown city
B11: South Africa
C12: Cape Town
C13: Durban
C14: Johannesburg
A15: Americas
B16: Brazil
C17: Brasília
C18: Rio de Janeiro
C19: São Paulo
C20: Unknown city
B21: Canada
C22: Montreal
C23: Toronto
C24: Unknown city
C25: Vancouver
B26: USA
C27: Austin
C28: Chicago
C29: New York
C30: San Francisco
A31: Asia
B32: China
C33: Beijing
C34: Shanghai
C35: Shenzhen
C36: Unknown city
B37: India
C38: Bengaluru
C39: Delhi
C40: Hyderabad
C41: Mumbai
C42: Unknown city
B43: Japan
C44: Nagoya
C45: Osaka
C46: Tokyo
A47: Europe
B48: France
C49: Lyon
C50: Marseille
C51: Paris
B52: Germany
C53: Berlin
C54: Frankfurt
C55: Munich
B56: United Kingdom
C57: Birmingham
C58: London
C59: Manchester
C60: Unknown city
A61: Grand Total

Sheet 3.ProductCategory &PriceBands
A3: Count of Derived Price Band | B3: Derived Price Band
A4: ProductCategory | B4: High | C4: Low | D4: Medium | E4: Grand Total
A5: Accessories | B5: 25 | C5: 32 | D5: 31 | E5: 88
A6: Components | B6: 34 | C6: 31 | D6: 26 | E6: 91
A7: Laptops | B7: 37 | C7: 22 | D7: 23 | E7: 82
A8: Monitors | B8: 25 | C8: 35 | D8: 34 | E8: 94
A9: Networking | B9: 36 | C9: 27 | D9: 23 | E9: 86
A10: Phones | B10: 27 | C10: 30 | D10: 31 | E10: 88
A11: Printers | B11: 25 | C11: 42 | D11: 36 | E11: 103
A12: Grand Total | B12: 209 | C12: 219 | D12: 204 | E12: 632

Sheet 4. Cohort analysis
A3: Country | B3: Years | C3: OrderDate | D3: Sum of GrossRevenue
A4: Brazil | D4: 1037432.5
B5: 2023
C6: Jan | D6: 1801.4076
C7: Feb | D7: 24894.431
C8: Mar | D8: 24523.007
C9: Apr | D9: 12248.676
C10: May | D10: 27194.152
C11: Jun | D11: 46991.747
C12: Jul | D12: 93430.735
C13: Aug | D13: 37330.003
C14: Sep | D14: 7071.6331
C15: Oct | D15: 16213.633
C16: Nov | D16: 24161.263
C17: Dec | D17: 61471.697
B18: 2024
C19: Jan | D19: 8567.3925
C20: Feb | D20: 39239.198
C21: Mar | D21: 110.1492
C22: Apr | D22: 57491.063
C23: May | D23: 9469.7678
C24: Jun | D24: 41658.527
C25: Jul | D25: 10937.52
C26: Aug | D26: 41358.42
C27: Sep | D27: 85419.018
C28: Nov | D28: 11939.431
B29: 2025
C30: Jan | D30: 22987.328
C31: Feb | D31: 70563.592
C32: Mar | D32: 16257.34
C33: Apr | D33: 68920.107
C34: May | D34: 67158.245
C35: Jul | D35: 38096.184
C36: Aug | D36: 45754.744
C37: Sep | D37: 24172.045
A38: Canada | D38: 882622.98
B39: 2023
C40: Jan | D40: 4141.76
C41: Feb | D41: 26150.364
C42: Mar | D42: 17453.344
C43: Apr | D43: 15618.845
C44: Jun | D44: 46226.12
C45: Jul | D45: 29536.716
C46: Aug | D46: 52625.804
C47: Sep | D47: 15530.93
C48: Oct | D48: 27756.432
C49: Dec | D49: 14466.951
B50: 2024
C51: Jan | D51: 19139.594
C52: Feb | D52: 9774.3888
C53: Mar | D53: 21931.504
C54: May | D54: 17930.495
C55: Jun | D55: 55516.604
C56: Jul | D56: 79082.507
C57: Aug | D57: 7466.3064
C58: Sep | D58: 64160.245
C59: Nov | D59: 60697.471
C60: Dec | D60: 20713.04
B61: 2025
C62: Feb | D62: 8128.5188
C63: Apr | D63: 7901.5042
C64: May | D64: 76122.593
C65: Jun | D65: 5335.5656
C66: Jul | D66: 141645.57
C67: Aug | D67: 24972.288
C68: Sep | D68: 12597.522
A69: China | D69: 894790.38
B70: 2023
C71: Jan | D71: 11406.96
C72: Feb | D72: 10869.183
C73: Mar | D73: 13437.3
C74: Apr | D74: 23379.011
C75: May | D75: 49097.717
C76: Jun | D76: 5769.2758
C77: Aug | D77: 64096.735
C78: Sep | D78: 14108.168
C79: Oct | D79: 62366.338
C80: Dec | D80: 23668.56
B81: 2024
C82: Feb | D82: 79081.561
C83: Mar | D83: 45749.976
C84: Apr | D84: 14197.064
C85: Jun | D85: 70180.56
C86: Jul | D86: 50774.407
C87: Sep | D87: 21270.483
C88: Oct | D88: 68861.98
C89: Nov | D89: 4071.8
C90: Dec | D90: 77129.274
B91: 2025
C92: Jan | D92: 56274.474
C93: Mar | D93: 9378.6258
C94: May | D94: 9684.8756
C95: Jun | D95: 55548.647
C96: Jul | D96: 20703.052
C97: Aug | D97: 33684.351
A98: France | D98: 821488.83
B99: 2023
C100: Jan | D100: 9847.2359
C101: Feb | D101: 39546.775
C102: Apr | D102: 40811.052
...

Sheet 5. ABC Analysis
A3: ProductCategory | B3: SKU | C3: Sum of GrossRevenue | D3: Percentage | E3: Cumulative% | F3: ABC Analysis
A4: Accessories | C4: 1394856.8 | D4: =SUM(D5:D92) -> 1
B5: ACC-6626 | C5: 79082.507 | D5: =C5/$C$4 -> 0.056695788 | E5: =D5 -> 0.056695788 | F5: =IF(E5<=80%,"A",IF(E5<=95%,"B",IF(E5<=100%,"C"," "))) -> A
B6: ACC-1770 | C6: 63480.9 | D6: =C6/$C$4 -> 0.045510692 | E6: =E5+D6 -> 0.10220648 | F6: =IF(E6<=80%,"A",IF(E6<=95%,"B",IF(E6<=100%,"C"," "))) -> A
B7: ACC-2988 | C7: 53034.364 | D7: =C7/$C$4 -> 0.038021367 | E7: =E6+D7 -> 0.14022785 | F7: =IF(E7<=80%,"A",IF(E7<=95%,"B",IF(E7<=100%,"C"," "))) -> A
B8: ACC-9283 | C8: 46450.26 | D8: =C8/$C$4 -> 0.033301095 | E8: =E7+D8 -> 0.17352894 | F8: =IF(E8<=80%,"A",IF(E8<=95%,"B",IF(E8<=100%,"C"," "))) -> A
B9: ACC-9533 | C9: 43084.872 | D9: =C9/$C$4 -> 0.030888383 | E9: =E8+D9 -> 0.20441733 | F9: =IF(E9<=80%,"A",IF(E9<=95%,"B",IF(E9<=100%,"C"," "))) -> A
B10: ACC-8098 | C10: 38096.184 | D10: =C10/$C$4 -> 0.027311896 | E10: =E9+D10 -> 0.23172922 | F10: =IF(E10<=80%,"A",IF(E10<=95%,"B",IF(E10<=100%,"C"," "))) -> A
B11: ACC-4490 | C11: 35396.278 | D11: =C11/$C$4 -> 0.02537628 | E11: =E10+D11 -> 0.2571055 | F11: =IF(E11<=80%,"A",IF(E11<=95%,"B",IF(E11<=100%,"C"," "))) -> A
B12: ACC-7838 | C12: 35167.745 | D12: =C12/$C$4 -> 0.02521244 | E12: =E11+D12 -> 0.28231794 | F12: =IF(E12<=80%,"A",IF(E12<=95%,"B",IF(E12<=100%,"C"," "))) -> A
B13: ACC-5177 | C13: 34139.16 | D13: =C13/$C$4 -> 0.024475028 | E13: =E12+D13 -> 0.30679297 | F13: =IF(E13<=80%,"A",IF(E13<=95%,"B",IF(E13<=100%,"C"," "))) -> A
B14: ACC-9162 | C14: 33062.236 | D14: =C14/$C$4 -> 0.023702961 | E14: =E13+D14 -> 0.33049593 | F14: =IF(E14<=80%,"A",IF(E14<=95%,"B",IF(E14<=100%,"C"," "))) -> A
B15: ACC-7078 | C15: 32086.376 | D15: =C15/$C$4 -> 0.023003347 | E15: =E14+D15 -> 0.35349928 | F15: =IF(E15<=80%,"A",IF(E15<=95%,"B",IF(E15<=100%,"C"," "))) -> A
B16: ACC-1375 | C16: 31513.085 | D16: =C16/$C$4 -> 0.022592344 | E16: =E15+D16 -> 0.37609162 | F16: =IF(E16<=80%,"A",IF(E16<=95%,"B",IF(E16<=100%,"C"," "))) -> A
B17: ACC-1659 | C17: 28386.016 | D17: =C17/$C$4 -> 0.020350487 | E17: =E16+D17 -> 0.39644211 | F17: =IF(E17<=80%,"A",IF(E17<=95%,"B",IF(E17<=100%,"C"," "))) -> A
... B92: ACC-6777 | C92: 18.65984 | D92: =C92/$C$4 -> 1.3377602e-05 | E92: =E91+D92 -> 1 | F92: =IF(E92<=80%,"A",IF(E92<=95%,"B",IF(E92<=100%,"C"," "))) -> C
A93: Components | C93: 1545647
B94: CMP-8851 | C94: 139277.83 | D94: =C94/$C$93 -> 0.090109728 | E94: =D94 -> 0.090109728 | F94: =IF(E94<=80%,"A",IF(E94<=95%,"B",IF(E94<=100%,"C"," "))) -> A
B95: CMP-3938 | C95: 84136.12 | D95: =C95/$C$93 -> 0.05443424 | E95: =E94+D95 -> 0.14454397 | F95: =IF(E95<=80%,"A",IF(E95<=95%,"B",IF(E95<=100%,"C"," "))) -> A
B96: CMP-2040 | C96: 65111.386 | D96: =C96/$C$93 -> 0.042125651 | E96: =E95+D96 -> 0.18666962 | F96: =IF(E96<=80%,"A",IF(E96<=95%,"B",IF(E96<=100%,"C"," "))) -> A
B97: CMP-3731 | C97: 60928.502 | D97: =C97/$C$93 -> 0.039419416 | E97: =E96+D97 -> 0.22608904 | F97: =IF(E97<=80%,"A",IF(E97<=95%,"B",IF(E97<=100%,"C"," "))) -> A
B98: CMP-8127 | C98: 50296.415 | D98: =C98/$C$93 -> 0.032540687 | E98: =E97+D98 -> 0.25862972 | F98: =IF(E98<=80%,"A",IF(E98<=95%,"B",IF(E98<=100%,"C"," "))) -> A
B99: CMP-2096 | C99: 48097.911 | D99: =C99/$C$93 -> 0.031118303 | E99: =E98+D99 -> 0.28974802 | F99: =IF(E99<=80%,"A",IF(E99<=95%,"B",IF(E99<=100%,"C"," "))) -> A
B100: CMP-5006 | C100: 41419.524 | D100: =C100/$C$93 -> 0.026797532 | E100: =E99+D100 -> 0.31654556 | F100: =IF(E100<=80%,"A",IF(E100<=95%,"B",IF(E100<=100%,"C"," "))) -> A
B101: CMP-1940 | C101: 40476.013 | D101: =C101/$C$93 -> 0.0261871 | E101: =E100+D101 -> 0.34273266 | F101: =IF(E101<=80%,"A",IF(E101<=95%,"B",IF(E101<=100%,"C"," "))) -> A
B102: CMP-8002 | C102: 33687.502 | D102: =C102/$C$93 -> 0.021795081 | E102: =E101+D102 -> 0.36452774 | F102: =IF(E102<=80%,"A",IF(E102<=95%,"B",IF(E102<=100%,"C"," "))) -> A
B103: CMP-1156 | C103: 33308.55 | D103: =C103/$C$93 -> 0.021549908 | E103: =E102+D103 -> 0.38607765 | F103: =IF(E103<=80%,"A",IF(E103<=95%,"B",IF(E103<=100%,"C"," "))) -> A
B104: CMP-6529 | C104: 32335.218 | D104: =C104/$C$93 -> 0.020920183 | E104: =E103+D104 -> 0.40699783 | F104: =IF(E104<=80%,"A",IF(E104<=95%,"B",IF(E104<=100%,"C"," "))) -> A
B105: CMP-6971 | C105: 27701.57 | D105: =C105/$C$93 -> 0.017922314 | E105: =E104+D105 -> 0.42492014 | F105: =IF(E105<=80%,"A",IF(E105<=95%,"B",IF(E105<=100%,"C"," "))) -> A
B106: CMP-6392 | C106: 27676.35 | D106: =C106/$C$93 -> 0.017905997 | E106: =E105+D106 -> 0.44282614 | F106: =IF(E106<=80%,"A",IF(E106<=95%,"B",IF(E106<=100%,"C"," "))) -> A
... B183: CMP-1632 | C183: 97.0154 | D183: =C183/$C$93 -> 6.2766854e-05 | E183: =E182+D183 -> 1 | F183: =IF(E183<=80%,"A",IF(E183<=95%,"B",IF(E183<=100%,"C"," "))) -> C
A184: Laptops | C184: 1711094.4
B185: LAP-8910 | C185: 102122.94 | D185: =C185/$C$184 -> 0.059682823 | E185: =D185 -> 0.059682823 | F185: =IF(E185<=80%,"A",IF(E185<=95%,"B",IF(E185<=100%,"C"," "))) -> A
B186: LAP-3904 | C186: 82514.712 | D186: =C186/$C$184 -> 0.048223355 | E186: =E185+D186 -> 0.10790618 | F186: =IF(E186<=80%,"A",IF(E186<=95%,"B",IF(E186<=100%,"C"," "))) -> A
B187: LAP-8214 | C187: 65119.33 | D187: =C187/$C$184 -> 0.038057123 | E187: =E186+D187 -> 0.1459633 | F187: =IF(E187<=80%,"A",IF(E187<=95%,"B",IF(E187<=100%,"C"," "))) -> A
B188: LAP-5763 | C188: 65066.934 | D188: =C188/$C$184 -> 0.038026502 | E188: =E187+D188 -> 0.1839898 | F188: =IF(E188<=80%,"A",IF(E188<=95%,"B",IF(E188<=100%,"C"," "))) -> A
B189: LAP-6499 | C189: 64192.977 | D189: =C189/$C$184 -> 0.037515743 | E189: =E188+D189 -> 0.22150555 | F189: =IF(E189<=80%,"A",IF(E189<=95%,"B",IF(E189<=100%,"C"," "))) -> A
B190: LAP-1739 | C190: 58526.831 | D190: =C190/$C$184 -> 0.034204327 | E190: =E189+D190 -> 0.25570987 | F190: =IF(E190<=80%,"A",IF(E190<=95%,"B",IF(E190<=100%,"C"," "))) -> A
B191: LAP-8825 | C191: 58057.65 | D191: =C191/$C$184 -> 0.033930127 | E191: =E190+D191 -> 0.28964 | F191: =IF(E191<=80%,"A",IF(E191<=95%,"B",IF(E191<=100%,"C"," "))) -> A
B192: LAP-7523 | C192: 44173.628 | D192: =C192/$C$184 -> 0.025816009 | E192: =E191+D192 -> 0.31545601 | F192: =IF(E192<=80%,"A",IF(E192<=95%,"B",IF(E192<=100%,"C"," "))) -> A
B193: LAP-1308 | C193: 42433.254 | D193: =C193/$C$184 -> 0.024798898 | E193: =E192+D193 -> 0.34025491 | F193: =IF(E193<=80%,"A",IF(E193<=95%,"B",IF(E193<=100%,"C"," "))) -> A
B194: LAP-1178 | C194: 41914.216 | D194: =C194/$C$184 -> 0.02449556 | E194: =E193+D194 -> 0.36475047 | F194: =IF(E194<=80%,"A",IF(E194<=95%,"B",IF(E194<=100%,"C"," "))) -> A
B195: LAP-4483 | C195: 40563.322 | D195: =C195/$C$184 -> 0.023706069 | E195: =E194+D195 -> 0.38845654 | F195: =IF(E195<=80%,"A",IF(E195<=95%,"B",IF(E195<=100%,"C"," "))) -> A
B196: LAP-3490 | C196: 40139.875 | D196: =C196/$C$184 -> 0.023458598 | E196: =E195+D196 -> 0.41191513 | F196: =IF(E196<=80%,"A",IF(E196<=95%,"B",IF(E196<=100%,"C"," "))) -> A
B197: LAP-3385 | C197: 39263.703 | D197: =C197/$C$184 -> 0.022946544 | E197: =E196+D197 -> 0.43486168 | F197: =IF(E197<=80%,"A",IF(E197<=95%,"B",IF(E197<=100%,"C"," "))) -> A
... B265: LAP-3017 | C265: 266.17822 | D265: =C265/$C$184 -> 0.00015556022 | E265: =E264+D265 -> 1 | F265: =IF(E265<=80%,"A",IF(E265<=95%,"B",IF(E265<=100%,"C"," "))) -> C
A266: Monitors | C266: 1568482.2
B267: MON-6962 | C267: 92715.25 | D267: =C267/$C$266 -> 0.059111446 | E267: =D267 -> 0.059111446 | F267: =IF(E267<=80%,"A",IF(E267<=95%,"B",IF(E267<=100%,"C"," "))) -> A
B268: MON-2266 | C268: 87404.93 | D268: =C268/$C$266 -> 0.055725803 | E268: =E267+D268 -> 0.11483725 | F268: =IF(E268<=80%,"A",IF(E268<=95%,"B",IF(E268<=100%,"C"," "))) -> A
B269: MON-6699 | C269: 85637.74 | D269: =C269/$C$266 -> 0.054599115 | E269: =E268+D269 -> 0.16943636 | F269: =IF(E269<=80%,"A",IF(E269<=95%,"B",IF(E269<=100%,"C"," "))) -> A
B270: MON-5188 | C270: 72665.817 | D270: =C270/$C$266 -> 0.046328749 | E270: =E269+D270 -> 0.21576511 | F270: =IF(E270<=80%,"A",IF(E270<=95%,"B",IF(E270<=100%,"C"," "))) -> A
B271: MON-9662 | C271: 56176.778 | D271: =C271/$C$266 -> 0.035816012 | E271: =E270+D271 -> 0.25158112 | F271: =IF(E271<=80%,"A",IF(E271<=95%,"B",IF(E271<=100%,"C"," "))) -> A
B272: MON-5386 | C272: 45547.183 | D272: =C272/$C$266 -> 0.029039018 | E272: =E271+D272 -> 0.28062014 | F272: =IF(E272<=80%,"A",IF(E272<=95%,"B",IF(E272<=100%,"C"," "))) -> A
B273: MON-9967 | C273: 41106.801 | D273: =C273/$C$266 -> 0.026208012 | E273: =E272+D273 -> 0.30682816 | F273: =IF(E273<=80%,"A",IF(E273<=95%,"B",IF(E273<=100%,"C"," "))) -> A
B274: MON-9733 | C274: 38818.76 | D274: =C274/$C$266 -> 0.024749251 | E274: =E273+D274 -> 0.33157741 | F274: =IF(E274<=80%,"A",IF(E274<=95%,"B",IF(E274<=100%,"C"," "))) -> A
B275: MON-8651 | C275: 34632.106 | D275: =C275/$C$266 -> 0.022080012 | E275: =E274+D275 -> 0.35365742 | F275: =IF(E275<=80%,"A",IF(E275<=95%,"B",IF(E275<=100%,"C"," "))) -> A
B276: MON-4373 | C276: 32280.325 | D276: =C276/$C$266 -> 0.020580613 | E276: =E275+D276 -> 0.37423803 | F276: =IF(E276<=80%,"A",IF(E276<=95%,"B",IF(E276<=100%,"C"," "))) -> A
B277: MON-4925 | C277: 31680.795 | D277: =C277/$C$266 -> 0.020198377 | E277: =E276+D277 -> 0.39443641 | F277: =IF(E277<=80%,"A",IF(E277<=95%,"B",IF(E277<=100%,"C"," "))) -> A
B278: MON-6341 | C278: 31191.647 | D278: =C278/$C$266 -> 0.019886517 | E278: =E277+D278 -> 0.41432293 | F278: =IF(E278<=80%,"A",IF(E278<=95%,"B",IF(E278<=100%,"C"," "))) -> A
B279: MON-6310 | C279: 30799.274 | D279: =C279/$C$266 -> 0.019636355 | E279: =E278+D279 -> 0.43395928 | F279: =IF(E279<=80%,"A",IF(E279<=95%,"B",IF(E279<=100%,"C"," "))) -> A
... B360: MON-5444 | C360: 66.92076 | D360: =C360/$C$266 -> 4.2665935e-05 | E360: =E359+D360 -> 1 | F360: =IF(E360<=80%,"A",IF(E360<=95%,"B",IF(E360<=100%,"C"," "))) -> C
A361: Networking | C361: 1789271.7
B362: NET-2365 | C362: 109244 | D362: =C362/$C$361 -> 0.061055009 | E362: =D362 -> 0.061055009 | F362: =IF(E362<=80%,"A",IF(E362<=95%,"B",IF(E362<=100%,"C"," "))) -> A
B363: NET-5987 | C363: 82141.34 | D363: =C363/$C$361 -> 0.045907695 | E363: =E362+D363 -> 0.1069627 | F363: =IF(E363<=80%,"A",IF(E363<=95%,"B",IF(E363<=100%,"C"," "))) -> A
B364: NET-5523 | C364: 79548.756 | D364: =C364/$C$361 -> 0.044458735 | E364: =E363+D364 -> 0.15142144 | F364: =IF(E364<=80%,"A",IF(E364<=95%,"B",IF(E364<=100%,"C"," "))) -> A
B365: NET-1612 | C365: 66988.771 | D365: =C365/$C$361 -> 0.037439127 | E365: =E364+D365 -> 0.18886057 | F365: =IF(E365<=80%,"A",IF(E365<=95%,"B",IF(E365<=100%,"C"," "))) -> A
B366: NET-5018 | C366: 60292.805 | D366: =C366/$C$361 -> 0.033696842 | E366: =E365+D366 -> 0.22255741 | F366: =IF(E366<=80%,"A",IF(E366<=95%,"B",IF(E366<=100%,"C"," "))) -> A
B367: NET-1282 | C367: 51768.182 | D367: =C367/$C$361 -> 0.028932544 | E367: =E366+D367 -> 0.25148995 | F367: =IF(E367<=80%,"A",IF(E367<=95%,"B",IF(E367<=100%,"C"," "))) -> A
B368: NET-4735 | C368: 50090.397 | D368: =C368/$C$361 -> 0.027994853 | E368: =E367+D368 -> 0.27948481 | F368: =IF(E368<=80%,"A",IF(E368<=95%,"B",IF(E368<=100%,"C"," "))) -> A
B369: NET-3850 | C369: 49336.511 | D369: =C369/$C$361 -> 0.027573516 | E369: =E368+D369 -> 0.30705832 | F369: =IF(E369<=80%,"A",IF(E369<=95%,"B",IF(E369<=100%,"C"," "))) -> A
B370: NET-6036 | C370: 47962.718 | D370: =C370/$C$361 -> 0.026805721 | E370: =E369+D370 -> 0.33386404 | F370: =IF(E370<=80%,"A",IF(E370<=95%,"B",IF(E370<=100%,"C"," "))) -> A
B371: NET-3828 | C371: 47693.373 | D371: =C371/$C$361 -> 0.026655188 | E371: =E370+D371 -> 0.36051923 | F371: =IF(E371<=80%,"A",IF(E371<=95%,"B",IF(E371<=100%,"C"," "))) -> A
B372: NET-3535 | C372: 43553.493 | D372: =C372/$C$361 -> 0.024341464 | E372: =E371+D372 -> 0.38486069 | F372: =IF(E372<=80%,"A",IF(E372<=95%,"B",IF(E372<=100%,"C"," "))) -> A
B373: NET-1893 | C373: 40488.793 | D373: =C373/$C$361 -> 0.022628644 | E373: =E372+D373 -> 0.40748934 | F373: =IF(E373<=80%,"A",IF(E373<=95%,"B",IF(E373<=100%,"C"," "))) -> A
B374: NET-1699 | C374: 39686.418 | D374: =C374/$C$361 -> 0.022180208 | E374: =E373+D374 -> 0.42966955 | F374: =IF(E374<=80%,"A",IF(E374<=95%,"B",IF(E374<=100%,"C"," "))) -> A
... B447: NET-4241 | C447: 34.68906 | D447: =C447/$C$361 -> 1.9387251e-05 | E447: =E446+D447 -> 1 | F447: =IF(E447<=80%,"A",IF(E447<=95%,"B",IF(E447<=100%,"C"," "))) -> C
A448: Phones | C448: 1398841.5
B449: PHN-9677 | C449: 68665.574 | D449: =C449/$C$448 -> 0.04908746 | E449: =D449 -> 0.04908746 | F449: =IF(E449<=80%,"A",IF(E449<=95%,"B",IF(E449<=100%,"C"," "))) -> A
B450: PHN-8368 | C450: 52780.07 | D450: =C450/$C$448 -> 0.037731274 | E450: =E449+D450 -> 0.086818734 | F450: =IF(E450<=80%,"A",IF(E450<=95%,"B",IF(E450<=100%,"C"," "))) -> A
B451: PHN-4568 | C451: 42495.805 | D451: =C451/$C$448 -> 0.030379287 | E451: =E450+D451 -> 0.11719802 | F451: =IF(E451<=80%,"A",IF(E451<=95%,"B",IF(E451<=100%,"C"," "))) -> A
B452: PHN-7488 | C452: 41352.246 | D452: =C452/$C$448 -> 0.029561782 | E452: =E451+D452 -> 0.1467598 | F452: =IF(E452<=80%,"A",IF(E452<=95%,"B",IF(E452<=100%,"C"," "))) -> A
B453: PHN-5683 | C453: 41138.262 | D453: =C453/$C$448 -> 0.02940881 | E453: =E452+D453 -> 0.17616861 | F453: =IF(E453<=80%,"A",IF(E453<=95%,"B",IF(E453<=100%,"C"," "))) -> A
B454: PHN-4915 | C454: 38422.022 | D454: =C454/$C$448 -> 0.027467032 | E454: =E453+D454 -> 0.20363564 | F454: =IF(E454<=80%,"A",IF(E454<=95%,"B",IF(E454<=100%,"C"," "))) -> A
B455: PHN-8804 | C455: 37038.582 | D455: =C455/$C$448 -> 0.026478041 | E455: =E454+D455 -> 0.23011369 | F455: =IF(E455<=80%,"A",IF(E455<=95%,"B",IF(E455<=100%,"C"," "))) -> A
B456: PHN-1197 | C456: 35367.211 | D456: =C456/$C$448 -> 0.025283216 | E456: =E455+D456 -> 0.2553969 | F456: =IF(E456<=80%,"A",IF(E456<=95%,"B",IF(E456<=100%,"C"," "))) -> A
B457: PHN-6832 | C457: 34840.344 | D457: =C457/$C$448 -> 0.024906571 | E457: =E456+D457 -> 0.28030347 | F457: =IF(E457<=80%,"A",IF(E457<=95%,"B",IF(E457<=100%,"C"," "))) -> A
B458: PHN-8776 | C458: 34800.431 | D458: =C458/$C$448 -> 0.024878038 | E458: =E457+D458 -> 0.30518151 | F458: =IF(E458<=80%,"A",IF(E458<=95%,"B",IF(E458<=100%,"C"," "))) -> A
B459: PHN-6111 | C459: 33551.927 | D459: =C459/$C$448 -> 0.023985511 | E459: =E458+D459 -> 0.32916702 | F459: =IF(E459<=80%,"A",IF(E459<=95%,"B",IF(E459<=100%,"C"," "))) -> A
B460: PHN-1919 | C460: 33071.315 | D460: =C460/$C$448 -> 0.023641932 | E460: =E459+D460 -> 0.35280895 | F460: =IF(E460<=80%,"A",IF(E460<=95%,"B",IF(E460<=100%,"C"," "))) -> A
B461: PHN-4677 | C461: 33017.42 | D461: =C461/$C$448 -> 0.023603404 | E461: =E460+D461 -> 0.37641236 | F461: =IF(E461<=80%,"A",IF(E461<=95%,"B",IF(E461<=100%,"C"," "))) -> A
... B536: PHN-3803 | C536: 76.13872 | D536: =C536/$C$448 -> 5.4429843e-05 | E536: =E535+D536 -> 1 | F536: =IF(E536<=80%,"A",IF(E536<=95%,"B",IF(E536<=100%,"C"," "))) -> C
A537: Printers | C537: 1616102.7
B538: PRN-1654 | C538: 66260.314 | D538: =C538/$C$537 -> 0.041000065 | E538: =D538 -> 0.041000065 | F538: =IF(E538<=80%,"A",IF(E538<=95%,"B",IF(E538<=100%,"C"," "))) -> A
B539: PRN-6308 | C539: 58091.635 | D539: =C539/$C$537 -> 0.035945511 | E539: =E538+D539 -> 0.076945576 | F539: =IF(E539<=80%,"A",IF(E539<=95%,"B",IF(E539<=100%,"C"," "))) -> A
B540: PRN-7019 | C540: 55880.484 | D540: =C540/$C$537 -> 0.034577311 | E540: =E539+D540 -> 0.11152289 | F540: =IF(E540<=80%,"A",IF(E540<=95%,"B",IF(E540<=100%,"C"," "))) -> A
B541: PRN-2407 | C541: 50545.319 | D541: =C541/$C$537 -> 0.031276057 | E541: =E540+D541 -> 0.14279894 | F541: =IF(E541<=80%,"A",IF(E541<=95%,"B",IF(E541<=100%,"C"," "))) -> A
B542: PRN-9490 | C542: 43907.94 | D542: =C542/$C$537 -> 0.027169029 | E542: =E541+D542 -> 0.16996797 | F542: =IF(E542<=80%,"A",IF(E542<=95%,"B",IF(E542<=100%,"C"," "))) -> A
B543: PRN-8970 | C543: 43209.006 | D543: =C543/$C$537 -> 0.026736548 | E543: =E542+D543 -> 0.19670452 | F543: =IF(E543<=80%,"A",IF(E543<=95%,"B",IF(E543<=100%,"C"," "))) -> A
B544: PRN-2293 | C544: 40325.31 | D544: =C544/$C$537 -> 0.024952196 | E544: =E543+D544 -> 0.22165672 | F544: =IF(E544<=80%,"A",IF(E544<=95%,"B",IF(E544<=100%,"C"," "))) -> A
B545: PRN-6131 | C545: 39810.328 | D545: =C545/$C$537 -> 0.024633539 | E545: =E544+D545 -> 0.24629026 | F545: =IF(E545<=80%,"A",IF(E545<=95%,"B",IF(E545<=100%,"C"," "))) -> A
...

Sheet 6. Salesperson productivity
A3: Salesperson | B3: Distinct Count of OrderID | C3: Sum of GrossRevenue | D3: Sum of GrossProfit | E3: Distinct Count of Month | F3: Revenue/Order | G3: Orders/Month | H3: Gross Profit/Order
A4: A. Patel | B4: 46 | C4: 877159.52 | D4: 281944.47 | E4: 12 | F4: =C4/B4 -> 19068.685 | G4: =B4/E4 -> 3.8333333 | H4: =D4/B4 -> 6129.2276
A5: B. Chen | B5: 48 | C5: 893735.66 | D5: 315969.97 | E5: 12 | F5: =C5/B5 -> 18619.493 | G5: =B5/E5 -> 4 | H5: =D5/B5 -> 6582.7077
A6: C. Otieno | B6: 37 | C6: 685111.86 | D6: 225695.02 | E6: 12 | F6: =C6/B6 -> 18516.537 | G6: =B6/E6 -> 3.0833333 | H6: =D6/B6 -> 6099.8654
A7: D. Smith | B7: 38 | C7: 594149.69 | D7: 168406.43 | E7: 11 | F7: =C7/B7 -> 15635.518 | G7: =B7/E7 -> 3.4545455 | H7: =D7/B7 -> 4431.7481
A8: E. Garcia | B8: 34 | C8: 543846.44 | D8: 204981.34 | E8: 12 | F8: =C8/B8 -> 15995.484 | G8: =B8/E8 -> 2.8333333 | H8: =D8/B8 -> 6028.863
A9: F. Müller | B9: 51 | C9: 812637.17 | D9: 251733.01 | E9: 12 | F9: =C9/B9 -> 15934.062 | G9: =B9/E9 -> 4.25 | H9: =D9/B9 -> 4935.9414
A10: G. Dubois | B10: 30 | C10: 510653.71 | D10: 172441.87 | E10: 11 | F10: =C10/B10 -> 17021.79 | G10: =B10/E10 -> 2.7272727 | H10: =D10/B10 -> 5748.0624
A11: H. Kim | B11: 45 | C11: 760776.21 | D11: 200228.72 | E11: 12 | F11: =C11/B11 -> 16906.138 | G11: =B11/E11 -> 3.75 | H11: =D11/B11 -> 4449.5272
A12: I. Johnson | B12: 38 | C12: 556078.75 | D12: 154934.77 | E12: 11 | F12: =C12/B12 -> 14633.651 | G12: =B12/E12 -> 3.4545455 | H12: =D12/B12 -> 4077.2309
A13: J. Njeri | B13: 50 | C13: 802384.66 | D13: 273113.11 | E13: 11 | F13: =C13/B13 -> 16047.693 | G13: =B13/E13 -> 4.5454545 | H13: =D13/B13 -> 5462.2622
A14: K. Singh | B14: 44 | C14: 883348.13 | D14: 278762.27 | E14: 12 | F14: =C14/B14 -> 20076.094 | G14: =B14/E14 -> 3.6666667 | H14: =D14/B14 -> 6335.5061
A15: L. Okafor | B15: 46 | C15: 853038.52 | D15: 269716.55 | E15: 12 | F15: =C15/B15 -> 18544.316 | G15: =B15/E15 -> 3.8333333 | H15: =D15/B15 -> 5863.4033
... A20: Grand Total | B20: 631 | C20: 11024296 | D20: 3496548.5 | E20: 12 | F20: =C20/B20 -> 17471.151 | G20: =B20/E20 -> 52.583333 | H20: =D20/B20 -> 5541.2813

Sheet 7.Channel mix & cannibalization
A3: Region | B3: Channel | C3: Sum of GrossRevenue
A4: Africa | C4: 2612548.9
B5: Direct | C5: 461428.96
B6: Distributor | C6: 623894.11
B7: Marketplace | C7: 527467.87
B8: Not provided | C8: 32716.924
B9: Online | C9: 433406.34
B10: Retail | C10: 533634.72
A11: Americas | C11: 2688750
B12: Direct | C12: 751887.69
B13: Distributor | C13: 568425.23
B14: Marketplace | C14: 366375.93
B15: Not provided | C15: 9256.14
B16: Online | C16: 689951.45
B17: Retail | C17: 302853.58
A18: Asia | C18: 2841471.9
B19: Direct | C19: 642428.79
B20: Distributor | C20: 509418.81
B21: Marketplace | C21: 541441.74
B22: Not provided | C22: 41379.395
B23: Online | C23: 413661.51
B24: Retail | C24: 693141.68
A25: Europe | C25: 2881525.3
B26: Direct | C26: 842614.45
B27: Distributor | C27: 318736.67
B28: Marketplace | C28: 632884.44
B29: Not provided | C29: 18050.446
B30: Online | C30: 585406.72
B31: Retail | C31: 483832.61
A32: Grand Total | C32: 11024296

Sheet 8. Service level proxy
A1: On-Time | B1: Ontime
A3: Count of On-Time | B3: ProductCategory
A4: Country | B4: Accessories | C4: Components | D4: Laptops | E4: Monitors | F4: Networking | G4: Phones | H4: Printers | I4: Grand Total
A5: Brazil | B5: 0.023255814 | C5: 0.0058139535 | D5: 0.0058139535 | E5: 0.01744186 | F5: 0.011627907 | G5: 0.029069767 | H5: 0.011627907 | I5: 0.10465116
A6: Canada | B6: 0.011627907 | C6: 0.01744186 | D6: 0.011627907 | E6: 0 | F6: 0 | G6: 0 | H6: 0.011627907 | I6: 0.052325581
A7: China | B7: 0.01744186 | C7: 0 | D7: 0.0058139535 | E7: 0.0058139535 | F7: 0.023255814 | G7: 0.0058139535 | H7: 0 | I7: 0.058139535
A8: France | B8: 0.0058139535 | C8: 0.01744186 | D8: 0.011627907 | E8: 0.01744186 | F8: 0.011627907 | G8: 0 | H8: 0.011627907 | I8: 0.075581395
A9: Germany | B9: 0.023255814 | C9: 0.011627907 | D9: 0.011627907 | E9: 0.0058139535 | F9: 0.0058139535 | G9: 0.0058139535 | H9: 0.0058139535 | I9: 0.069767442
A10: India | B10: 0.011627907 | C10: 0.011627907 | D10: 0.0058139535 | E10: 0.011627907 | F10: 0.0058139535 | G10: 0.011627907 | H10: 0.011627907 | I10: 0.069767442
A11: Japan | B11: 0.0058139535 | C11: 0.01744186 | D11: 0.01744186 | E11: 0.011627907 | F11: 0.0058139535 | G11: 0.0058139535 | H11: 0.01744186 | I11: 0.081395349
A12: Kenya | B12: 0.023255814 | C12: 0.0058139535 | D12: 0.040697674 | E12: 0 | F12: 0.011627907 | G12: 0.011627907 | H12: 0.0058139535 | I12: 0.098837209
A13: Nigeria | B13: 0.034883721 | C13: 0.011627907 | D13: 0.01744186 | E13: 0.01744186 | F13: 0.0058139535 | G13: 0.0058139535 | H13: 0.01744186 | I13: 0.11046512
A14: South Africa | B14: 0.011627907 | C14: 0.029069767 | D14: 0.011627907 | E14: 0.0058139535 | F14: 0.011627907 | G14: 0.011627907 | H14: 0.0058139535 | I14: 0.087209302
A15: United Kingdom | B15: 0.0058139535 | C15: 0.011627907 | D15: 0.023255814 | E15: 0.011627907 | F15: 0.011627907 | G15: 0.0058139535 | H15: 0.01744186 | I15: 0.087209302
A16: USA | B16: 0.011627907 | C16: 0.011627907 | D16: 0.0058139535 | E16: 0.0058139535 | F16: 0.029069767 | G16: 0.0058139535 | H16: 0.034883721 | I16: 0.10465116
A17: Grand Total | B17: 0.18604651 | C17: 0.15116279 | D17: 0.16860465 | E17: 0.11046512 | F17: 0.13372093 | G17: 0.098837209 | H17: 0.15116279 | I17: 1

Sheet 9. Price Compliance
A1: DiscountPct> 20% | B1: High Discount
A3: Count of OrderID | B3: Salesperson
A4: Region | B4: A. Patel | C4: B. Chen | D4: C. Otieno | E4: D. Smith | F4: E. Garcia | G4: F. Müller | H4: G. Dubois | I4: H. Kim | J4: I. Johnson | K4: J. Njeri | L4: K. Singh | M4: L. Okafor | N4: M. Rossi | O4: N. Brown | P4: O. Wang | Q4: Unknown | R4: Grand Total
A5: Africa | B5: 3 | C5: 0 | D5: 2 | E5: 2 | F5: 1 | G5: 0 | H5: 0 | I5: 1 | J5: 2 | K5: 3 | L5: 0 | M5: 2 | N5: 5 | O5: 0 | P5: 0 | Q5: 1 | R5: 22
A6: Americas | B6: 5 | C6: 1 | D6: 2 | E6: 4 | F6: 0 | G6: 1 | H6: 1 | I6: 0 | J6: 5 | K6: 0 | L6: 1 | M6: 3 | N6: 2 | O6: 1 | P6: 0 | Q6: 1 | R6: 27
A7: Asia | B7: 0 | C7: 2 | D7: 3 | E7: 1 | F7: 0 | G7: 3 | H7: 1 | I7: 2 | J7: 1 | K7: 2 | L7: 1 | M7: 3 | N7: 0 | O7: 1 | P7: 4 | Q7: 0 | R7: 24
A8: Europe | B8: 1 | C8: 2 | D8: 1 | E8: 1 | F8: 2 | G8: 0 | H8: 1 | I8: 1 | J8: 1 | K8: 1 | L8: 2 | M8: 0 | N8: 1 | O8: 3 | P8: 0 | Q8: 0 | R8: 17
A9: Grand Total | B9: 9 | C9: 5 | D9: 8 | E9: 8 | F9: 3 | G9: 4 | H9: 3 | I9: 4 | J9: 9 | K9: 6 | L9: 4 | M9: 8 | N9: 8 | O9: 5 | P9: 4 | Q9: 2 | R9: 90

Sheet 10. Whatif Control pannel
B1: DiscountPct
A2: Global Discout Cap(0%-25%) | B2: =F2/100 -> 0.23 | F2: 23
A6: UnitCost Inflation factor(0%-15%) | B6: =F6/100 -> 0.12 | F6: 12
A10: Quantity Uplift(0%-20%) | B10: =F10/100 -> 0.2 | F10: 20
A13: METRICS COMPARISON
A14: Gross Revenue | B14: ='1. Staging Table'!AB637 -> 11024296
A15: WhatIf GrossRevenue | B15: ='1. Staging Table'!AC637 -> 14886303
A17: GrossProfit | B17: ='1. Staging Table'!AE637 -> 3496548.5
A18: WhatIf GrossProfit | B18: ='1. Staging Table'!AF637 -> 7358555.4

Sheet 11. Revenue by Month pivottable
A3: Month | B3: Sum of GrossRevenue
A4: Jan | B4: 701241.31
A5: Feb | B5: 978103.94
A6: Mar | B6: 798978.3
A7: Apr | B7: 947246.58
A8: May | B8: 1262173.9
A9: Jun | B9: 1316182.1
A10: Jul | B10: 1313062.3
A11: Aug | B11: 1089608.8
A12: Sep | B12: 661159.43
A13: Oct | B13: 658776.06 | L13: =GETPIVOTDATA("GrossRevenue",$A$3,"Month",4)/GETPIVOTDATA("GrossRevenue",$A$3) -> #REF!
A14: Nov | B14: 543953.69
A15: Dec | B15: 753809.8
A16: Grand Total | B16: 11024296

Sheet 12.Profit by Region and Channel
A3: Region | B3: Channel | C3: Gross Profit
A4: Africa | C4: 852576.93
B5: Direct | C5: 177919.82
B6: Distributor | C6: 192042.35
B7: Marketplace | C7: 164839.3
B8: Not provided | C8: 16237.344
B9: Online | C9: 145453.95
B10: Retail | C10: 156084.17
A11: Americas | C11: 862340.77
B12: Direct | C12: 258674.93
B13: Distributor | C13: 175298.68
B14: Marketplace | C14: 96609.648
B15: Not provided | C15: 777.96
B16: Online | C16: 261943.84
B17: Retail | C17: 69035.709
A18: Asia | C18: 831257.73
B19: Direct | C19: 229217.48
B20: Distributor | C20: 151146.75
B21: Marketplace | C21: 128045.01
B22: Not provided | C22: 20547.545
B23: Online | C23: 149042.39
B24: Retail | C24: 153258.56
A25: Europe | C25: 950373.07
B26: Direct | C26: 292716.95
B27: Distributor | C27: 105550.85
B28: Marketplace | C28: 174900.72
B29: Not provided | C29: 8028.7065
B30: Online | C30: 200067.16
B31: Retail | C31: 169108.67
A32: Grand Total | C32: 3496548.5

Sheet 13.Top 10 SKUs by Revenue
A3: SKU | B3: Sum of GrossRevenue
A4: NET-5523 | B4: 79548.756
A5: NET-5987 | B5: 82141.34
A6: LAP-3904 | B6: 82514.712
A7: CMP-3938 | B7: 84136.12
A8: MON-6699 | B8: 85637.74
A9: MON-2266 | B9: 87404.93
A10: MON-6962 | B10: 92715.25
A11: LAP-8910 | B11: 102122.94
A12: NET-2365 | B12: 109244
A13: CMP-8851 | B13: 139277.83
A14: Grand Total | B14: 944743.62

Sheet 14. Discount Outliers
A3: OrderID | B3: DiscountPct > 0.25
A4: ORD-2023-261081 | B4: 0.565
A5: ORD-2023-290279 | B5: 0.257
A6: ORD-2023-368449 | B6: 0.357
A7: ORD-2023-382272 | B7: 0.343
A8: ORD-2023-422918 | B8: 0.292
A9: ORD-2023-521818 | B9: 0.344
A10: ORD-2023-613287 | B10: 0.265
A11: ORD-2023-766015 | B11: 0.282
A12: ORD-2023-825084 | B12: 0.299
A13: ORD-2023-944052 | B13: 0.27
A14: ORD-2024-155337 | B14: 0.278
A15: ORD-2024-232632 | B15: 0.259
... A35: Grand Total | B35: 9.091

Sheet 15. DASHBOARD
